Workbook

Sheet Cover
W4: Hallo
D5: Gale Suer
D6: Financial Analyst
D12: SaaS Operating, 3-Statement & Valuation Financial Model
D13: Anarion Systems BV | 24-Month Driver-Based Forecast
D17: Table of Contents | L17: Model Integrity Checks
D19: Executive Dashboard | L19: Cash Flow Statement | R19: =IF(SUM('Operational Model'!G78:AD78)<>0,1,0) -> 0
D20: Inputs | L20: Balance Sheet | R20: =IF(SUM('Operational Model'!G118:AD118)<>0,1,0) -> 0
D21: Operational Model | L21: Revenue Forecast | R21: =IF(SUM('Operational Model'!G166:AD166)<>0,1,0) -> 0
D22: Valuation | L22: Headcount Forecast | R22: =IF(SUM('Operational Model'!G263:AD264)<>0,1,0) -> 0
L23: Cash & Fundraising Analysis | R23: =IF(SUM('Operational Model'!G345:AD349)<>0,1,0) -> 0
L24: Deferred Revenue Schedule | R24: =IF(SUM('Operational Model'!G422:AD423)<>0,1,0) -> 0
L25: PP&E & Depreciation Schedule | R25: =IF(SUM('Operational Model'!G464:AD464)<>0,1,0) -> 0
D30: Contact Details: | L30: Core Capabilities
D32: Tel. | E32: +31648370031 | L32: Driver-Based Forecasting · SaaS Metrics & KPI Reporting · Headcount Planning
D33: E-mail | E33: Gale.suer@outlook.com | L33: Cash & Runway Analysis · Scenario & Sensitivity Analysis · Business Valuation

Sheet Executive Dashboard
B1: Gale Suer - Financial Analyst
B3: Growth Performance | AB3: Graphing Data
B5: All figures in EUR thousands unless stated | AB5: All figures in EUR thousands unless stated | AF5: 2026 | AG5: 2026 | AH5: 2026 | AI5: 2026 | AJ5: 2026 | AK5: 2026 | AL5: 2026 | AM5: 2026 | AN5: 2026 | AO5: 2026 | AP5: 2026 | AQ5: 2026 | AR5: 2027 | AS5: 2027 | AT5: 2027 | AU5: 2027 | AV5: 2027 | AW5: 2027 | AX5: 2027 | AY5: 2027 | AZ5: 2027 | BA5: 2027 | BB5: 2027 | BC5: 2027
AF6: 1 | AG6: 1 | AH6: 1 | AI6: 2 | AJ6: 2 | AK6: 2 | AL6: 3 | AM6: 3 | AN6: 3 | AO6: 4 | AP6: 4 | AQ6: 4 | AR6: 1 | AS6: 1 | AT6: 1 | AU6: 2 | AV6: 2 | AW6: 2 | AX6: 3 | AY6: 3 | AZ6: 3 | BA6: 4 | BB6: 4 | BC6: 4
B7: Driver Switch | AF7: 46053 | AG7: 46081 | AH7: 46112 | AI7: 46142 | AJ7: 46173 | AK7: 46203 | AL7: 46234 | AM7: 46265 | AN7: 46295 | AO7: 46326 | AP7: 46356 | AQ7: 46387 | AR7: 46418 | AS7: 46446 | AT7: 46477 | AU7: 46507 | AV7: 46538 | AW7: 46568 | AX7: 46599 | AY7: 46630 | AZ7: 46660 | BA7: 46691 | BB7: 46721 | BC7: 46752
C10: Monthly Recurring Revenue | P10: Annual Recurring Revenue | AB10: Growth Performance
AB11: MRR | AF11: ='Operational Model'!G155 -> 913.2228 | AG11: ='Operational Model'!H155 -> 933.64625 | AH11: ='Operational Model'!I155 -> 953.82026 | AI11: ='Operational Model'!J155 -> 973.79366 | AJ11: ='Operational Model'!K155 -> 993.61427 | AK11: ='Operational Model'!L155 -> 1013.329 | AL11: ='Operational Model'!M155 -> 1032.9839 | AM11: ='Operational Model'!N155 -> 1052.6242 | ... BC11: ='Operational Model'!AD155 -> 1461.3423
AB12: MRR Growth | AF12: ='Operational Model'!G156 -> 0.023218824 | AG12: ='Operational Model'!H156 -> 0.022364149 | AH12: ='Operational Model'!I156 -> 0.021607766 | AI12: ='Operational Model'!J156 -> 0.020940422 | AJ12: ='Operational Model'!K156 -> 0.02035402 | AK12: ='Operational Model'!L156 -> 0.019841432 | AL12: ='Operational Model'!M156 -> 0.019396351 | AM12: ='Operational Model'!N156 -> 0.019013163 | ... BC12: ='Operational Model'!AD156 -> 0.020881645
AB13: ARR | AF13: ='Operational Model'!G163 -> 10958.674 | AG13: ='Operational Model'!H163 -> 11203.755 | AH13: ='Operational Model'!I163 -> 11445.843 | AI13: ='Operational Model'!J163 -> 11685.524 | AJ13: ='Operational Model'!K163 -> 11923.371 | AK13: ='Operational Model'!L163 -> 12159.948 | AL13: ='Operational Model'!M163 -> 12395.807 | AM13: ='Operational Model'!N163 -> 12631.49 | ... BC13: ='Operational Model'!AD163 -> 17536.108
AB14: ARR Growth | AF14: ='Operational Model'!G164 -> 0.023218824 | AG14: ='Operational Model'!H164 -> 0.022364149 | AH14: ='Operational Model'!I164 -> 0.021607766 | AI14: ='Operational Model'!J164 -> 0.020940422 | AJ14: ='Operational Model'!K164 -> 0.02035402 | AK14: ='Operational Model'!L164 -> 0.019841432 | AL14: ='Operational Model'!M164 -> 0.019396351 | AM14: ='Operational Model'!N164 -> 0.019013163 | ... BC14: ='Operational Model'!AD164 -> 0.020881645
AB21: New MRR | AF21: ='Operational Model'!G151 -> 36.75 | AG21: ='Operational Model'!H151 -> 36.824342 | AH21: ='Operational Model'!I151 -> 36.943102 | AI21: ='Operational Model'!J151 -> 37.106104 | AJ21: ='Operational Model'!K151 -> 37.313227 | AK21: ='Operational Model'!L151 -> 37.564403 | AL21: ='Operational Model'!M151 -> 37.859621 | AM21: ='Operational Model'!N151 -> 38.198922 | ... BC21: ='Operational Model'!AD151 -> 51.286265
AB22: Lost MRR | AF22: ='Operational Model'!G152 -> -17.85 | AG22: ='Operational Model'!H152 -> -18.264456 | AH22: ='Operational Model'!I152 -> -18.672925 | AI22: ='Operational Model'!J152 -> -19.076405 | AJ22: ='Operational Model'!K152 -> -19.475873 | AK22: ='Operational Model'!L152 -> -19.872285 | AL22: ='Operational Model'!M152 -> -20.26658 | AM22: ='Operational Model'!N152 -> -20.659678 | ... BC22: ='Operational Model'!AD152 -> -25.766123
AB23: Net New MRR | AF23: ='Operational Model'!G153 -> 18.9 | AG23: ='Operational Model'!H153 -> 18.559886 | AH23: ='Operational Model'!I153 -> 18.270177 | AI23: ='Operational Model'!J153 -> 18.029699 | AJ23: ='Operational Model'!K153 -> 17.837353 | AK23: ='Operational Model'!L153 -> 17.692118 | AL23: ='Operational Model'!M153 -> 17.593041 | AM23: ='Operational Model'!N153 -> 17.539244 | ... BC23: ='Operational Model'!AD153 -> 25.520142
C37: MRR Inflow/Outflow | P37: MRR Inflow/Outflow
B65: Customer Growth & Retention | AB65: Graphing Data
B67: All figures in EUR thousands unless stated | AB67: All figures in EUR thousands unless stated | AF67: 2026 | AG67: 2026 | AH67: 2026 | AI67: 2026 | AJ67: 2026 | AK67: 2026 | AL67: 2026 | AM67: 2026 | AN67: 2026 | AO67: 2026 | AP67: 2026 | AQ67: 2026 | AR67: 2027 | AS67: 2027 | AT67: 2027 | AU67: 2027 | AV67: 2027 | AW67: 2027 | AX67: 2027 | AY67: 2027 | AZ67: 2027 | BA67: 2027 | BB67: 2027 | BC67: 2027
B68: {=CONCATENATE("Model Running: ",INDEX(Inputs!$B$15:$B$17,Inputs!$D$8)," Drivers")} -> Model Running: Base Case Drivers | AF68: 1 | AG68: 1 | AH68: 1 | AI68: 2 | AJ68: 2 | AK68: 2 | AL68: 3 | AM68: 3 | AN68: 3 | AO68: 4 | AP68: 4 | AQ68: 4 | AR68: 1 | AS68: 1 | AT68: 1 | AU68: 2 | AV68: 2 | AW68: 2 | AX68: 3 | AY68: 3 | AZ68: 3 | BA68: 4 | BB68: 4 | BC68: 4
AF69: 46053 | AG69: 46081 | AH69: 46112 | AI69: 46142 | AJ69: 46173 | AK69: 46203 | AL69: 46234 | AM69: 46265 | AN69: 46295 | AO69: 46326 | AP69: 46356 | AQ69: 46387 | AR69: 46418 | AS69: 46446 | AT69: 46477 | AU69: 46507 | AV69: 46538 | AW69: 46568 | AX69: 46599 | AY69: 46630 | AZ69: 46660 | BA69: 46691 | BB69: 46721 | BC69: 46752
C71: Customer Bridge FY2026 | P71: Customer Bridge FY2027
AB72: Customer Growth & Retention
AB73: Gross Churn | AF73: =Inputs!F31 -> 0.02 | AG73: =Inputs!G31 -> 0.02 | AH73: =Inputs!H31 -> 0.02 | AI73: =Inputs!I31 -> 0.02 | AJ73: =Inputs!J31 -> 0.02 | AK73: =Inputs!K31 -> 0.02 | AL73: =Inputs!L31 -> 0.02 | AM73: =Inputs!M31 -> 0.02 | ... BC73: =Inputs!AC31 -> 0.018
AB74: ARPU | AF74: ='Operational Model'!G143 -> 1052.1 | AG74: ='Operational Model'!H143 -> 1054.2042 | AH74: ='Operational Model'!I143 -> 1056.3126 | AI74: ='Operational Model'!J143 -> 1058.4252 | AJ74: ='Operational Model'!K143 -> 1060.5421 | AK74: ='Operational Model'!L143 -> 1062.6632 | AL74: ='Operational Model'!M143 -> 1064.7885 | AM74: ='Operational Model'!N143 -> 1066.9181 | ... BC74: ='Operational Model'!AD143 -> 1114.8416
AB75: Beginning Customers | AF75: ='Operational Model'!G135 -> 850 | AG75: ='Operational Model'!H135 -> 868 | AH75: ='Operational Model'!I135 -> 885.6408 | AI75: ='Operational Model'!J135 -> 902.97158 | AJ75: ='Operational Model'!K135 -> 920.0401 | AK75: ='Operational Model'!L135 -> 936.89283 | AL75: ='Operational Model'!M135 -> 953.57498 | AM75: ='Operational Model'!N135 -> 970.13059 | ... BC75: ='Operational Model'!AD135 -> 1287.8472
AB76: New Customers | AF76: ='Operational Model'!G136 -> 35 | AG76: ='Operational Model'!H136 -> 35.0008 | AH76: ='Operational Model'!I136 -> 35.043592 | AI76: ='Operational Model'!J136 -> 35.127957 | AJ76: ='Operational Model'!K136 -> 35.253531 | AK76: ='Operational Model'!L136 -> 35.420002 | AL76: ='Operational Model'!M136 -> 35.627113 | AM76: ='Operational Model'!N136 -> 35.874657 | ... BC76: ='Operational Model'!AD136 -> 46.141196
AB77: Lost Customers | AF77: ='Operational Model'!G137 -> -17 | AG77: ='Operational Model'!H137 -> -17.36 | AH77: ='Operational Model'!I137 -> -17.712816 | AI77: ='Operational Model'!J137 -> -18.059432 | AJ77: ='Operational Model'!K137 -> -18.400802 | AK77: ='Operational Model'!L137 -> -18.737857 | AL77: ='Operational Model'!M137 -> -19.0715 | AM77: ='Operational Model'!N137 -> -19.402612 | ... BC77: ='Operational Model'!AD137 -> -23.18125
AB78: Ending Customers | AF78: ='Operational Model'!G138 -> 868 | AG78: ='Operational Model'!H138 -> 885.6408 | AH78: ='Operational Model'!I138 -> 902.97158 | AI78: ='Operational Model'!J138 -> 920.0401 | AJ78: ='Operational Model'!K138 -> 936.89283 | AK78: ='Operational Model'!L138 -> 953.57498 | AL78: ='Operational Model'!M138 -> 970.13059 | AM78: ='Operational Model'!N138 -> 986.60264 | ... BC78: ='Operational Model'!AD138 -> 1310.8072
AB79: Net Customer Adds | AF79: ='Operational Model'!G146 -> 18 | AG79: ='Operational Model'!H146 -> 17.6408 | AH79: ='Operational Model'!I146 -> 17.330776 | AI79: ='Operational Model'!J146 -> 17.068526 | AJ79: ='Operational Model'!K146 -> 16.852729 | AK79: ='Operational Model'!L146 -> 16.682146 | AL79: ='Operational Model'!M146 -> 16.555614 | AM79: ='Operational Model'!N146 -> 16.472045 | ... BC79: ='Operational Model'!AD146 -> 22.959946
AB80: Customer Growth | AF80: ='Operational Model'!G148 -> 0.021176471 | AG80: ='Operational Model'!H148 -> 0.020323502 | AH80: ='Operational Model'!I148 -> 0.019568629 | AI80: ='Operational Model'!J148 -> 0.018902617 | AJ80: ='Operational Model'!K148 -> 0.018317385 | AK80: ='Operational Model'!L148 -> 0.017805821 | AL80: ='Operational Model'!M148 -> 0.017361628 | AM80: ='Operational Model'!N148 -> 0.016979204 | ... BC80: ='Operational Model'!AD148 -> 0.01782816
AF84: FY2026 | AG84: FY2027
AB86: Beginning Customers | AF86: =AF75 -> 850 | AG86: =AR75 -> 1052.4803
AB87: New Customers | AF87: =SUM(AF76:AQ76) -> 429.12597 | AG87: =SUM(AR76:BC76) -> 510.69576
AB88: Lost Customers | AF88: =SUM(AF77:AQ77) -> -226.64563 | AG88: =SUM(AR77:BC77) -> -252.36893
AB89: Ending Customers | AF89: =AQ78 -> 1052.4803 | AG89: =BC78 -> 1310.8072
C99: Net Customer Adds | P99: ARPU & Gross Churn
B127: Operating Efficiency | AB127: Graphing Data
B129: All figures in EUR thousands unless stated | AB129: All figures in EUR thousands unless stated | AF129: 2026 | AG129: 2026 | AH129: 2026 | AI129: 2026 | AJ129: 2026 | AK129: 2026 | AL129: 2026 | AM129: 2026 | AN129: 2026 | AO129: 2026 | AP129: 2026 | AQ129: 2026 | AR129: 2027 | AS129: 2027 | AT129: 2027 | AU129: 2027 | AV129: 2027 | AW129: 2027 | AX129: 2027 | AY129: 2027 | AZ129: 2027 | BA129: 2027 | BB129: 2027 | BC129: 2027
B130: {=CONCATENATE("Model Running: ",INDEX(Inputs!$B$15:$B$17,Inputs!$D$8)," Drivers")} -> Model Running: Base Case Drivers | AF130: 1 | AG130: 1 | AH130: 1 | AI130: 2 | AJ130: 2 | AK130: 2 | AL130: 3 | AM130: 3 | AN130: 3 | AO130: 4 | AP130: 4 | AQ130: 4 | AR130: 1 | AS130: 1 | AT130: 1 | AU130: 2 | AV130: 2 | AW130: 2 | AX130: 3 | AY130: 3 | AZ130: 3 | BA130: 4 | BB130: 4 | BC130: 4
AF131: 46053 | AG131: 46081 | AH131: 46112 | AI131: 46142 | AJ131: 46173 | AK131: 46203 | AL131: 46234 | AM131: 46265 | AN131: 46295 | AO131: 46326 | AP131: 46356 | AQ131: 46387 | AR131: 46418 | AS131: 46446 | AT131: 46477 | AU131: 46507 | AV131: 46538 | AW131: 46568 | AX131: 46599 | AY131: 46630 | AZ131: 46660 | BA131: 46691 | BB131: 46721 | BC131: 46752
C133: Expenses | P133: EBITDA
AB134: Operating Efficiency
AB135: Customer Success Personnel | AF135: =-'Operational Model'!G12 -> 89.924167 | AG135: =-'Operational Model'!H12 -> 92.8725 | AH135: =-'Operational Model'!I12 -> 95.820833 | AI135: =-'Operational Model'!J12 -> 98.769167 | AJ135: =-'Operational Model'!K12 -> 101.7175 | AK135: =-'Operational Model'!L12 -> 104.66583 | AL135: =-'Operational Model'!M12 -> 107.61417 | AM135: =-'Operational Model'!N12 -> 110.5625 | ... BC135: =-'Operational Model'!AD12 -> 143.87867
AB136: Hosting & Infrastructure | AF136: =-'Operational Model'!G13 -> 45.66114 | AG136: =-'Operational Model'!H13 -> 46.682313 | AH136: =-'Operational Model'!I13 -> 47.691013 | AI136: =-'Operational Model'!J13 -> 48.689683 | AJ136: =-'Operational Model'!K13 -> 49.680714 | AK136: =-'Operational Model'!L13 -> 50.66645 | AL136: =-'Operational Model'!M13 -> 51.649195 | AM136: =-'Operational Model'!N13 -> 52.631209 | ... BC136: =-'Operational Model'!AD13 -> 73.067116
AB137: Sales & Marketing | AF137: =-'Operational Model'!G19 -> 309.96161 | AG137: =-'Operational Model'!H19 -> 319.17506 | AH137: =-'Operational Model'!I19 -> 328.35359 | AI137: =-'Operational Model'!J19 -> 337.50403 | AJ137: =-'Operational Model'!K19 -> 346.63308 | AK137: =-'Operational Model'!L19 -> 355.74731 | AL137: =-'Operational Model'!M19 -> 364.85316 | AM137: =-'Operational Model'!N19 -> 373.95697 | ... BC137: =-'Operational Model'!AD19 -> 483.15575
AB138: R&D/Product | AF138: =-'Operational Model'!G20 -> 306.77917 | AG138: =-'Operational Model'!H20 -> 315.42083 | AH138: =-'Operational Model'!I20 -> 324.0625 | AI138: =-'Operational Model'!J20 -> 332.70417 | AJ138: =-'Operational Model'!K20 -> 341.34583 | AK138: =-'Operational Model'!L20 -> 349.9875 | AL138: =-'Operational Model'!M20 -> 358.62917 | AM138: =-'Operational Model'!N20 -> 367.27083 | ... BC138: =-'Operational Model'!AD20 -> 455.84792
AB139: G&A | AF139: =-'Operational Model'!G21 -> 204.6552 | AG139: =-'Operational Model'!H21 -> 208.68004 | AH139: =-'Operational Model'!I21 -> 212.67994 | AI139: =-'Operational Model'!J21 -> 216.65978 | AJ139: =-'Operational Model'!K21 -> 220.62434 | AK139: =-'Operational Model'!L21 -> 224.57832 | AL139: =-'Operational Model'!M21 -> 228.52631 | AM139: =-'Operational Model'!N21 -> 232.47283 | ... BC139: =-'Operational Model'!AD21 -> 275.25206
AB140: Gross Margin % | AF140: ='Operational Model'!G16 -> 0.85153097 | AG140: ='Operational Model'!H16 -> 0.8505271 | AH140: ='Operational Model'!I16 -> 0.84953995 | AI140: ='Operational Model'!J16 -> 0.8485728 | AJ140: ='Operational Model'!K16 -> 0.84762879 | AK140: ='Operational Model'!L16 -> 0.84671091 | AL140: ='Operational Model'!M16 -> 0.84582203 | AM140: ='Operational Model'!N16 -> 0.84496489 | ... BC140: ='Operational Model'!AD16 -> 0.85154349
AB141: EBITDA | AF141: ='Operational Model'!G22 -> -43.758479 | AG141: ='Operational Model'!H22 -> -49.184495 | AH141: ='Operational Model'!I22 -> -54.787615 | AI141: ='Operational Model'!J22 -> -60.533169 | AJ141: ='Operational Model'!K22 -> -66.387198 | AK141: ='Operational Model'!L22 -> -72.316406 | AL141: ='Operational Model'!M22 -> -78.288105 | AM141: ='Operational Model'!N22 -> -84.270165 | ... BC141: ='Operational Model'!AD22 -> 30.140804
AB142: EBITDA Margin % | AF142: ='Operational Model'!G24 -> -0.047916542 | AG142: ='Operational Model'!H24 -> -0.052680011 | AH142: ='Operational Model'!I24 -> -0.057440188 | AI142: ='Operational Model'!J24 -> -0.062162213 | AJ142: ='Operational Model'!K24 -> -0.066813853 | AK142: ='Operational Model'!L24 -> -0.07136518 | AL142: ='Operational Model'!M24 -> -0.075788311 | AM142: ='Operational Model'!N24 -> -0.080057219 | ... BC142: ='Operational Model'!AD24 -> 0.020625423
AB143: ARR | AF143: ='Operational Model'!G163 -> 10958.674 | AG143: ='Operational Model'!H163 -> 11203.755 | AH143: ='Operational Model'!I163 -> 11445.843 | AI143: ='Operational Model'!J163 -> 11685.524 | AJ143: ='Operational Model'!K163 -> 11923.371 | AK143: ='Operational Model'!L163 -> 12159.948 | AL143: ='Operational Model'!M163 -> 12395.807 | AM143: ='Operational Model'!N163 -> 12631.49 | ... BC143: ='Operational Model'!AD163 -> 17536.108
AB144: Average FTE | AF144: =AVERAGE('Operational Model'!G205,'Operational Model'!G207) -> 96.4 | AG144: =AVERAGE('Operational Model'!H205,'Operational Model'!H207) -> 99.2 | AH144: =AVERAGE('Operational Model'!I205,'Operational Model'!I207) -> 102 | AI144: =AVERAGE('Operational Model'!J205,'Operational Model'!J207) -> 104.8 | AJ144: =AVERAGE('Operational Model'!K205,'Operational Model'!K207) -> 107.6 | AK144: =AVERAGE('Operational Model'!L205,'Operational Model'!L207) -> 110.4 | AL144: =AVERAGE('Operational Model'!M205,'Operational Model'!M207) -> 113.2 | AM144: =AVERAGE('Operational Model'!N205,'Operational Model'!N207) -> 116 | ... BC144: =AVERAGE('Operational Model'!AD205,'Operational Model'!AD207) -> 144.65
AB145: Ending FTE | AF145: ='Operational Model'!G255 -> 97.8 | AG145: ='Operational Model'!H255 -> 100.6 | AH145: ='Operational Model'!I255 -> 103.4 | AI145: ='Operational Model'!J255 -> 106.2 | AJ145: ='Operational Model'!K255 -> 109 | AK145: ='Operational Model'!L255 -> 111.8 | AL145: ='Operational Model'!M255 -> 114.6 | AM145: ='Operational Model'!N255 -> 117.4 | ... BC145: ='Operational Model'!AD255 -> 145.35
AB146: Revenue per FTE | AF146: =AF143/AF144 -> 113.67919 | AG146: =AG143/AG144 -> 112.94108 | AH146: =AH143/AH144 -> 112.21415 | AI146: =AI143/AI144 -> 111.50309 | AJ146: =AJ143/AJ144 -> 110.812 | AK146: =AK143/AK144 -> 110.14446 | AL146: =AL143/AL144 -> 109.50359 | AM146: =AM143/AM144 -> 108.89216 | ... BC146: =BC143/BC144 -> 121.2313
AF150: 1 | AG150: 2 | AH150: 3 | AI150: 4 | AJ150: 1 | AK150: 2 | AL150: 3 | AM150: 4
AB151: LTV/CAC | AE151: (ratio) | AF151: ='Operational Model'!G526 -> 6.1479097 | AG151: ='Operational Model'!H526 -> 5.7163531 | AH151: ='Operational Model'!I526 -> 5.4072674 | AI151: ='Operational Model'!J526 -> 5.1932969 | AJ151: ='Operational Model'!K526 -> 5.9908886 | AK151: ='Operational Model'!L526 -> 6.0432611 | AL151: ='Operational Model'!M526 -> 6.1411451 | AM151: ='Operational Model'!N526 -> 6.2615252
AB152: CAC Payback | AE152: (months) | AF152: ='Operational Model'!G527 -> 8.1328456 | AG152: ='Operational Model'!H527 -> 8.7468355 | AH152: ='Operational Model'!I527 -> 9.2468148 | AI152: ='Operational Model'!J527 -> 9.6277955 | AJ152: ='Operational Model'!K527 -> 9.2733415 | AK152: ='Operational Model'!L527 -> 9.1929763 | AL152: ='Operational Model'!M527 -> 9.0464489 | AM152: ='Operational Model'!N527 -> 8.8725277
AF156: FY2026 | AG156: FY2027
AB158: ARR Growth | AF158: ='Operational Model'!R163/'Operational Model'!G158-1 -> 0.26825833 | AG158: ='Operational Model'!AD163/'Operational Model'!S158-1 -> 0.29102903
AB159: EBITDA Margin % | AF159: =SUM(AF141:AQ141)/SUM(AF11:AQ11) -> -0.07376971 | AG159: =SUM(AR141:BC141)/SUM(AR11:BC11) -> -0.028590125
AB160: Rule of 40 | AF160: =AF158+AF159 -> 0.19448862 | AG160: =AG158+AG159 -> 0.26243891
C161: Margins | P161: Headcount & Revenue per FTE | AB161: Benchmark Rule of 40 | AF161: 0.4 | AG161: 0.4
AB162: CAC | AF162: ='Operational Model'!G532 -> 8.0595937 | AG162: ='Operational Model'!H532 -> 8.4471246
AB163: LTV | AF163: ='Operational Model'!G533 -> 45.009387 | AG163: ='Operational Model'!H533 -> 51.620669
C189: Rule of 40 | P189: Unit Economics
Q194: CAC
Q196: =AF156 -> FY2026 | R196: =AG156 -> FY2027
Q198: =AF162 -> 8.0595937 | R198: =AG162 -> 8.4471246
Q205: LTV
Q207: =AF156 -> FY2026 | R207: =AG156 -> FY2027
Q209: =AF163 -> 45.009387 | R209: =AG163 -> 51.620669
B217: Liquidity & Cash Flow | AB217: Graphing Data
B219: All figures in EUR thousands unless stated | AB219: All figures in EUR thousands unless stated | AF219: 2026 | AG219: 2026 | AH219: 2026 | AI219: 2026 | AJ219: 2026 | AK219: 2026 | AL219: 2026 | AM219: 2026 | AN219: 2026 | AO219: 2026 | AP219: 2026 | AQ219: 2026 | AR219: 2027 | AS219: 2027 | AT219: 2027 | AU219: 2027 | AV219: 2027 | AW219: 2027 | AX219: 2027 | AY219: 2027 | AZ219: 2027 | BA219: 2027 | BB219: 2027 | BC219: 2027
B220: {=CONCATENATE("Model Running: ",INDEX(Inputs!$B$15:$B$17,Inputs!$D$8)," Drivers")} -> Model Running: Base Case Drivers | AF220: 1 | AG220: 1 | AH220: 1 | AI220: 2 | AJ220: 2 | AK220: 2 | AL220: 3 | AM220: 3 | AN220: 3 | AO220: 4 | AP220: 4 | AQ220: 4 | AR220: 1 | AS220: 1 | AT220: 1 | AU220: 2 | AV220: 2 | AW220: 2 | AX220: 3 | AY220: 3 | AZ220: 3 | BA220: 4 | BB220: 4 | BC220: 4
AF221: 46053 | AG221: 46081 | AH221: 46112 | AI221: 46142 | AJ221: 46173 | AK221: 46203 | AL221: 46234 | AM221: 46265 | AN221: 46295 | AO221: 46326 | AP221: 46356 | AQ221: 46387 | AR221: 46418 | AS221: 46446 | AT221: 46477 | AU221: 46507 | AV221: 46538 | AW221: 46568 | AX221: 46599 | AY221: 46630 | AZ221: 46660 | BA221: 46691 | BB221: 46721 | BC221: 46752
C223: Free Cash Flow & Cash Balance | P223: Other Cash Metrics
AB224: Liquidity & Cash Flow
AB225: Ending Cash | AF225: ='Operational Model'!G75 -> 3854.2627 | AG225: ='Operational Model'!H75 -> 3850.5066 | AH225: ='Operational Model'!I75 -> 3840.0634 | AI225: ='Operational Model'!J75 -> 3822.9124 | AJ225: ='Operational Model'!K75 -> 3799.0632 | AK225: ='Operational Model'!L75 -> 3768.5553 | AL225: ='Operational Model'!M75 -> 3731.4577 | AM225: ='Operational Model'!N75 -> 3687.8686 | ... BC225: ='Operational Model'!AD75 -> 3655.8765
X226: Quarterly Trend | AB226: Free Cash Flow | AF226: ='Operational Model'!G336 -> 4.262716 | AG226: ='Operational Model'!H336 -> -3.7561331 | AH226: ='Operational Model'!I336 -> -10.443219 | AI226: ='Operational Model'!J336 -> -17.150978 | AJ226: ='Operational Model'!K336 -> -23.849157 | AK226: ='Operational Model'!L336 -> -30.507882 | AL226: ='Operational Model'!M336 -> -37.097619 | AM226: ='Operational Model'!N336 -> -43.589128 | ... BC226: ='Operational Model'!AD336 -> 89.522946
AB227: Net Monthly Cash Burn | AF227: ='Operational Model'!G340 -> 0 | AG227: ='Operational Model'!H340 -> 3.7561331 | AH227: ='Operational Model'!I340 -> 10.443219 | AI227: ='Operational Model'!J340 -> 17.150978 | AJ227: ='Operational Model'!K340 -> 23.849157 | AK227: ='Operational Model'!L340 -> 30.507882 | AL227: ='Operational Model'!M340 -> 37.097619 | AM227: ='Operational Model'!N340 -> 43.589128 | ... BC227: ='Operational Model'!AD340 -> 0
P228: ENDING CASH | T228: ENDING CASH
Q230: =AQ225 -> 3451.5719 | U230: =AU225 -> 3320.0183
AF231: 1 | AG231: 2 | AH231: 3 | AI231: 4 | AJ231: 1 | AK231: 2 | AL231: 3 | AM231: 4
Q232: =AQ221 -> 46387 | U232: =BC221 -> 46752
AB233: Ending Cash | AF233: =AH225 -> 3840.0634 | AG233: =AK225 -> 3768.5553 | AH233: =AN225 -> 3637.9152 | AI233: =AQ225 -> 3451.5719 | AJ233: =AT225 -> 3336.2945 | AK233: =AW225 -> 3323.3554 | AL233: =AZ225 -> 3425.5684 | AM233: =BC225 -> 3655.8765
AB234: Average Monthly Cash Burn | AF234: =AVERAGE(AF227,AG227,AH227) -> 4.7331172 | AG234: =AVERAGE(AI227,AJ227,AK227) -> 23.836006 | AH234: =AVERAGE(AL227,AM227,AN227) -> 43.546723 | AI234: =AVERAGE(AO227,AP227,AQ227) -> 62.114434 | AJ234: =AVERAGE(AR227,AS227,AT227) -> 38.425807 | AK234: =AVERAGE(AU227,AV227,AW227) -> 6.9154101 | AL234: =AVERAGE(AX227,AY227,AZ227) -> 0 | AM234: =AVERAGE(BA227,BB227,BC227) -> 0
X235: Quarterly Trend
P237: NET MONTHLY CASH BURN | T237: NET MONTHLY CASH BURN
AF238: FY2026 | AG238: FY2027
Q239: =AQ227 -> 67.996117 | U239: =BC227 -> 0
AB240: FCF Breakeven Month | AF240: ='Operational Model'!G353 -> 46568
Q241: =AQ221 -> 46387 | U241: =BC221 -> 46752
P245: FCF Breakeven Month: | T245: =AF240 -> 46568
T246: =IF(T245="-","✗ Outside forecast","✓ Within forecast") -> ✓ Within forecast
B251: Funding & Runway | AB251: Graphing Data
B253: All figures in EUR thousands unless stated | AB253: All figures in EUR thousands unless stated | AF253: 2026 | AG253: 2026 | AH253: 2026 | AI253: 2026 | AJ253: 2026 | AK253: 2026 | AL253: 2026 | AM253: 2026 | AN253: 2026 | AO253: 2026 | AP253: 2026 | AQ253: 2026 | AR253: 2027 | AS253: 2027 | AT253: 2027 | AU253: 2027 | AV253: 2027 | AW253: 2027 | AX253: 2027 | AY253: 2027 | AZ253: 2027 | BA253: 2027 | BB253: 2027 | BC253: 2027
B254: {=CONCATENATE("Model Running: ",INDEX(Inputs!$B$15:$B$17,Inputs!$D$8)," Drivers")} -> Model Running: Base Case Drivers | AF254: 1 | AG254: 1 | AH254: 1 | AI254: 2 | AJ254: 2 | AK254: 2 | AL254: 3 | AM254: 3 | AN254: 3 | AO254: 4 | AP254: 4 | AQ254: 4 | AR254: 1 | AS254: 1 | AT254: 1 | AU254: 2 | AV254: 2 | AW254: 2 | AX254: 3 | AY254: 3 | AZ254: 3 | BA254: 4 | BB254: 4 | BC254: 4
AF255: 46053 | AG255: 46081 | AH255: 46112 | AI255: 46142 | AJ255: 46173 | AK255: 46203 | AL255: 46234 | AM255: 46265 | AN255: 46295 | AO255: 46326 | AP255: 46356 | AQ255: 46387 | AR255: 46418 | AS255: 46446 | AT255: 46477 | AU255: 46507 | AV255: 46538 | AW255: 46568 | AX255: 46599 | AY255: 46630 | AZ255: 46660 | BA255: 46691 | BB255: 46721 | BC255: 46752
C257: Runway | P257: Other Funding & Runway Metrics
AB258: Funding & Runway
AB259: Pre-Funding Runway | AF259: =IF('Operational Model'!G341=" ",NA(),MIN('Operational Model'!G341,36)) -> #N/A | AG259: =IF('Operational Model'!H341=" ",NA(),MIN('Operational Model'!H341,36)) -> 36 | AH259: =IF('Operational Model'!I341=" ",NA(),MIN('Operational Model'!I341,36)) -> 36 | AI259: =IF('Operational Model'!J341=" ",NA(),MIN('Operational Model'!J341,36)) -> 36 | AJ259: =IF('Operational Model'!K341=" ",NA(),MIN('Operational Model'!K341,36)) -> 36 | AK259: =IF('Operational Model'!L341=" ",NA(),MIN('Operational Model'!L341,36)) -> 36 | AL259: =IF('Operational Model'!M341=" ",NA(),MIN('Operational Model'!M341,36)) -> 36 | AM259: =IF('Operational Model'!N341=" ",NA(),MIN('Operational Model'!N341,36)) -> 36 | ... BC259: =IF('Operational Model'!AD341=" ",NA(),MIN('Operational Model'!AD341,36)) -> #N/A
AB260: Funding Threshold | AF260: =Inputs!$F$112 -> 18 | AG260: =Inputs!$F$112 -> 18 | AH260: =Inputs!$F$112 -> 18 | AI260: =Inputs!$F$112 -> 18 | AJ260: =Inputs!$F$112 -> 18 | AK260: =Inputs!$F$112 -> 18 | AL260: =Inputs!$F$112 -> 18 | AM260: =Inputs!$F$112 -> 18 | ... BC260: =Inputs!$F$112 -> 18
...

Sheet Inputs
B1: Gale Suer - Financial Analyst
B3: Scenario & Fixed Drivers
B5: All figures in EUR thousands unless stated
F7: =YEAR(F9) -> 2026 | G7: =YEAR(G9) -> 2026 | H7: =YEAR(H9) -> 2026 | I7: =YEAR(I9) -> 2026 | J7: =YEAR(J9) -> 2026 | K7: =YEAR(K9) -> 2026 | L7: =YEAR(L9) -> 2026 | M7: =YEAR(M9) -> 2026 | ... AC7: =YEAR(AC9) -> 2027
B8: Driver Switch | D8: 2 | F8: =CHOOSE(MONTH(F9),1,1,1,2,2,2,3,3,3,4,4,4) -> 1 | G8: =CHOOSE(MONTH(G9),1,1,1,2,2,2,3,3,3,4,4,4) -> 1 | H8: =CHOOSE(MONTH(H9),1,1,1,2,2,2,3,3,3,4,4,4) -> 1 | I8: =CHOOSE(MONTH(I9),1,1,1,2,2,2,3,3,3,4,4,4) -> 2 | J8: =CHOOSE(MONTH(J9),1,1,1,2,2,2,3,3,3,4,4,4) -> 2 | K8: =CHOOSE(MONTH(K9),1,1,1,2,2,2,3,3,3,4,4,4) -> 2 | L8: =CHOOSE(MONTH(L9),1,1,1,2,2,2,3,3,3,4,4,4) -> 3 | M8: =CHOOSE(MONTH(M9),1,1,1,2,2,2,3,3,3,4,4,4) -> 3 | ... AC8: =CHOOSE(MONTH(AC9),1,1,1,2,2,2,3,3,3,4,4,4) -> 4
F9: =E203 -> 46053 | G9: =EOMONTH(F9,1) -> 46081 | H9: =EOMONTH(G9,1) -> 46112 | I9: =EOMONTH(H9,1) -> 46142 | J9: =EOMONTH(I9,1) -> 46173 | K9: =EOMONTH(J9,1) -> 46203 | L9: =EOMONTH(K9,1) -> 46234 | M9: =EOMONTH(L9,1) -> 46265 | N9: =EOMONTH(M9,1) -> 46295 | ... AC9: =EOMONTH(AB9,1) -> 46752
B11: Revenue Drivers
B13: Lead Growth | F13: {=INDEX(F15:F17,$D$8)+'Operational Model'!$Q$547} -> 0.03 | G13: {=INDEX(G15:G17,$D$8)+'Operational Model'!$Q$547} -> 0.03 | H13: {=INDEX(H15:H17,$D$8)+'Operational Model'!$Q$547} -> 0.03 | I13: {=INDEX(I15:I17,$D$8)+'Operational Model'!$Q$547} -> 0.03 | J13: {=INDEX(J15:J17,$D$8)+'Operational Model'!$Q$547} -> 0.03 | K13: {=INDEX(K15:K17,$D$8)+'Operational Model'!$Q$547} -> 0.03 | L13: {=INDEX(L15:L17,$D$8)+'Operational Model'!$Q$547} -> 0.03 | M13: {=INDEX(M15:M17,$D$8)+'Operational Model'!$Q$547} -> 0.03 | ... AC13: {=INDEX(AC15:AC17,$D$8)+'Operational Model'!$Q$547} -> 0.025
B15: Best Case | F15: 0.05 | G15: 0.05 | H15: 0.05 | I15: 0.05 | J15: 0.05 | K15: 0.05 | L15: 0.05 | M15: 0.05 | N15: 0.05 | O15: 0.05 | P15: 0.05 | Q15: 0.05 | R15: 0.04 | S15: 0.04 | T15: 0.04 | U15: 0.04 | V15: 0.04 | W15: 0.04 | X15: 0.04 | Y15: 0.04 | Z15: 0.04 | AA15: 0.04 | AB15: 0.04 | AC15: 0.04
B16: Base Case | F16: 0.03 | G16: 0.03 | H16: 0.03 | I16: 0.03 | J16: 0.03 | K16: 0.03 | L16: 0.03 | M16: 0.03 | N16: 0.03 | O16: 0.03 | P16: 0.03 | Q16: 0.03 | R16: 0.025 | S16: 0.025 | T16: 0.025 | U16: 0.025 | V16: 0.025 | W16: 0.025 | X16: 0.025 | Y16: 0.025 | Z16: 0.025 | AA16: 0.025 | AB16: 0.025 | AC16: 0.025
B17: Worst Case | F17: 0.01 | G17: 0.01 | H17: 0.01 | I17: 0.01 | J17: 0.01 | K17: 0.01 | L17: 0.01 | M17: 0.01 | N17: 0.01 | O17: 0.01 | P17: 0.01 | Q17: 0.01 | R17: 0.005 | S17: 0.005 | T17: 0.005 | U17: 0.005 | V17: 0.005 | W17: 0.005 | X17: 0.005 | Y17: 0.005 | Z17: 0.005 | AA17: 0.005 | AB17: 0.005 | AC17: 0.005
B19: Conversion Rate | F19: {=INDEX(F21:F23,$D$8)+'Operational Model'!$Q$548} -> 0.04 | G19: {=INDEX(G21:G23,$D$8)+'Operational Model'!$Q$548} -> 0.04 | H19: {=INDEX(H21:H23,$D$8)+'Operational Model'!$Q$548} -> 0.04 | I19: {=INDEX(I21:I23,$D$8)+'Operational Model'!$Q$548} -> 0.04 | J19: {=INDEX(J21:J23,$D$8)+'Operational Model'!$Q$548} -> 0.04 | K19: {=INDEX(K21:K23,$D$8)+'Operational Model'!$Q$548} -> 0.04 | L19: {=INDEX(L21:L23,$D$8)+'Operational Model'!$Q$548} -> 0.04 | M19: {=INDEX(M21:M23,$D$8)+'Operational Model'!$Q$548} -> 0.04 | ... AC19: {=INDEX(AC21:AC23,$D$8)+'Operational Model'!$Q$548} -> 0.042
B21: =$B$15 -> Best Case | F21: 0.05 | G21: 0.05 | H21: 0.05 | I21: 0.05 | J21: 0.05 | K21: 0.05 | L21: 0.05 | M21: 0.05 | N21: 0.05 | O21: 0.05 | P21: 0.05 | Q21: 0.05 | R21: 0.055 | S21: 0.055 | T21: 0.055 | U21: 0.055 | V21: 0.055 | W21: 0.055 | X21: 0.055 | Y21: 0.055 | Z21: 0.055 | AA21: 0.055 | AB21: 0.055 | AC21: 0.055
B22: =$B$16 -> Base Case | F22: 0.04 | G22: 0.04 | H22: 0.04 | I22: 0.04 | J22: 0.04 | K22: 0.04 | L22: 0.04 | M22: 0.04 | N22: 0.04 | O22: 0.04 | P22: 0.04 | Q22: 0.04 | R22: 0.042 | S22: 0.042 | T22: 0.042 | U22: 0.042 | V22: 0.042 | W22: 0.042 | X22: 0.042 | Y22: 0.042 | Z22: 0.042 | AA22: 0.042 | AB22: 0.042 | AC22: 0.042
B23: =$B$17 -> Worst Case | F23: 0.03 | G23: 0.03 | H23: 0.03 | I23: 0.03 | J23: 0.03 | K23: 0.03 | L23: 0.03 | M23: 0.03 | N23: 0.03 | O23: 0.03 | P23: 0.03 | Q23: 0.03 | R23: 0.028 | S23: 0.028 | T23: 0.028 | U23: 0.028 | V23: 0.028 | W23: 0.028 | X23: 0.028 | Y23: 0.028 | Z23: 0.028 | AA23: 0.028 | AB23: 0.028 | AC23: 0.028
B25: ARPU Growth | F25: {=INDEX(F27:F29,$D$8)+'Operational Model'!$Q$549} -> 0.002 | G25: {=INDEX(G27:G29,$D$8)+'Operational Model'!$Q$549} -> 0.002 | H25: {=INDEX(H27:H29,$D$8)+'Operational Model'!$Q$549} -> 0.002 | I25: {=INDEX(I27:I29,$D$8)+'Operational Model'!$Q$549} -> 0.002 | J25: {=INDEX(J27:J29,$D$8)+'Operational Model'!$Q$549} -> 0.002 | K25: {=INDEX(K27:K29,$D$8)+'Operational Model'!$Q$549} -> 0.002 | L25: {=INDEX(L27:L29,$D$8)+'Operational Model'!$Q$549} -> 0.002 | M25: {=INDEX(M27:M29,$D$8)+'Operational Model'!$Q$549} -> 0.002 | ... AC25: {=INDEX(AC27:AC29,$D$8)+'Operational Model'!$Q$549} -> 0.003
B27: =$B$15 -> Best Case | F27: 0.004 | G27: 0.004 | H27: 0.004 | I27: 0.004 | J27: 0.004 | K27: 0.004 | L27: 0.004 | M27: 0.004 | N27: 0.004 | O27: 0.004 | P27: 0.004 | Q27: 0.004 | R27: 0.005 | S27: 0.005 | T27: 0.005 | U27: 0.005 | V27: 0.005 | W27: 0.005 | X27: 0.005 | Y27: 0.005 | Z27: 0.005 | AA27: 0.005 | AB27: 0.005 | AC27: 0.005
B28: =$B$16 -> Base Case | F28: 0.002 | G28: 0.002 | H28: 0.002 | I28: 0.002 | J28: 0.002 | K28: 0.002 | L28: 0.002 | M28: 0.002 | N28: 0.002 | O28: 0.002 | P28: 0.002 | Q28: 0.002 | R28: 0.003 | S28: 0.003 | T28: 0.003 | U28: 0.003 | V28: 0.003 | W28: 0.003 | X28: 0.003 | Y28: 0.003 | Z28: 0.003 | AA28: 0.003 | AB28: 0.003 | AC28: 0.003
B29: =$B$17 -> Worst Case | F29: 0 | G29: 0 | H29: 0 | I29: 0 | J29: 0 | K29: 0 | L29: 0 | M29: 0 | N29: 0 | O29: 0 | P29: 0 | Q29: 0 | R29: 0 | S29: 0 | T29: 0 | U29: 0 | V29: 0 | W29: 0 | X29: 0 | Y29: 0 | Z29: 0 | AA29: 0 | AB29: 0 | AC29: 0
B31: Gross Customer Churn | F31: {=INDEX(F33:F35,$D$8)+'Operational Model'!$Q$550} -> 0.02 | G31: {=INDEX(G33:G35,$D$8)+'Operational Model'!$Q$550} -> 0.02 | H31: {=INDEX(H33:H35,$D$8)+'Operational Model'!$Q$550} -> 0.02 | I31: {=INDEX(I33:I35,$D$8)+'Operational Model'!$Q$550} -> 0.02 | J31: {=INDEX(J33:J35,$D$8)+'Operational Model'!$Q$550} -> 0.02 | K31: {=INDEX(K33:K35,$D$8)+'Operational Model'!$Q$550} -> 0.02 | L31: {=INDEX(L33:L35,$D$8)+'Operational Model'!$Q$550} -> 0.02 | M31: {=INDEX(M33:M35,$D$8)+'Operational Model'!$Q$550} -> 0.02 | ... AC31: {=INDEX(AC33:AC35,$D$8)+'Operational Model'!$Q$550} -> 0.018
B33: =$B$15 -> Best Case | F33: 0.01 | G33: 0.01 | H33: 0.01 | I33: 0.01 | J33: 0.01 | K33: 0.01 | L33: 0.01 | M33: 0.01 | N33: 0.01 | O33: 0.01 | P33: 0.01 | Q33: 0.01 | R33: 0.008 | S33: 0.008 | T33: 0.008 | U33: 0.008 | V33: 0.008 | W33: 0.008 | X33: 0.008 | Y33: 0.008 | Z33: 0.008 | AA33: 0.008 | AB33: 0.008 | AC33: 0.008
B34: =$B$16 -> Base Case | F34: 0.02 | G34: 0.02 | H34: 0.02 | I34: 0.02 | J34: 0.02 | K34: 0.02 | L34: 0.02 | M34: 0.02 | N34: 0.02 | O34: 0.02 | P34: 0.02 | Q34: 0.02 | R34: 0.018 | S34: 0.018 | T34: 0.018 | U34: 0.018 | V34: 0.018 | W34: 0.018 | X34: 0.018 | Y34: 0.018 | Z34: 0.018 | AA34: 0.018 | AB34: 0.018 | AC34: 0.018
B35: =$B$17 -> Worst Case | F35: 0.035 | G35: 0.035 | H35: 0.035 | I35: 0.035 | J35: 0.035 | K35: 0.035 | L35: 0.035 | M35: 0.035 | N35: 0.035 | O35: 0.035 | P35: 0.035 | Q35: 0.035 | R35: 0.035 | S35: 0.035 | T35: 0.035 | U35: 0.035 | V35: 0.035 | W35: 0.035 | X35: 0.035 | Y35: 0.035 | Z35: 0.035 | AA35: 0.035 | AB35: 0.035 | AC35: 0.035
B37: Headcount Drivers
B39: Account Executive Hires | F39: {=INDEX(F41:F43,$D$8)} -> 0.7 | G39: {=INDEX(G41:G43,$D$8)} -> 0.7 | H39: {=INDEX(H41:H43,$D$8)} -> 0.7 | I39: {=INDEX(I41:I43,$D$8)} -> 0.7 | J39: {=INDEX(J41:J43,$D$8)} -> 0.7 | K39: {=INDEX(K41:K43,$D$8)} -> 0.7 | L39: {=INDEX(L41:L43,$D$8)} -> 0.7 | M39: {=INDEX(M41:M43,$D$8)} -> 0.7 | ... AC39: {=INDEX(AC41:AC43,$D$8)} -> 0.4
B41: =$B$15 -> Best Case | F41: 1.5 | G41: 1.5 | H41: 1.5 | I41: 1.5 | J41: 1.5 | K41: 1.5 | L41: 1.5 | M41: 1.5 | N41: 1.5 | O41: 1.5 | P41: 1.5 | Q41: 1.5 | R41: 1.1 | S41: 1.1 | T41: 1.1 | U41: 1.1 | V41: 1.1 | W41: 1.1 | X41: 1.1 | Y41: 1.1 | Z41: 1.1 | AA41: 1.1 | AB41: 1.1 | AC41: 1.1
B42: =$B$16 -> Base Case | F42: 0.7 | G42: 0.7 | H42: 0.7 | I42: 0.7 | J42: 0.7 | K42: 0.7 | L42: 0.7 | M42: 0.7 | N42: 0.7 | O42: 0.7 | P42: 0.7 | Q42: 0.7 | R42: 0.4 | S42: 0.4 | T42: 0.4 | U42: 0.4 | V42: 0.4 | W42: 0.4 | X42: 0.4 | Y42: 0.4 | Z42: 0.4 | AA42: 0.4 | AB42: 0.4 | AC42: 0.4
B43: =$B$17 -> Worst Case | F43: 0 | G43: 0 | H43: 0 | I43: 0 | J43: 0 | K43: 0 | L43: 0 | M43: 0 | N43: 0 | O43: 0 | P43: 0 | Q43: 0 | R43: 0 | S43: 0 | T43: 0 | U43: 0 | V43: 0 | W43: 0 | X43: 0 | Y43: 0 | Z43: 0 | AA43: 0 | AB43: 0 | AC43: 0
B45: Sales Development Rep Hires | F45: {=INDEX(F47:F49,$D$8)} -> 0.3 | G45: {=INDEX(G47:G49,$D$8)} -> 0.3 | H45: {=INDEX(H47:H49,$D$8)} -> 0.3 | I45: {=INDEX(I47:I49,$D$8)} -> 0.3 | J45: {=INDEX(J47:J49,$D$8)} -> 0.3 | K45: {=INDEX(K47:K49,$D$8)} -> 0.3 | L45: {=INDEX(L47:L49,$D$8)} -> 0.3 | M45: {=INDEX(M47:M49,$D$8)} -> 0.3 | ... AC45: {=INDEX(AC47:AC49,$D$8)} -> 0.1
B47: =$B$15 -> Best Case | F47: 0.5 | G47: 0.5 | H47: 0.5 | I47: 0.5 | J47: 0.5 | K47: 0.5 | L47: 0.5 | M47: 0.5 | N47: 0.5 | O47: 0.5 | P47: 0.5 | Q47: 0.5 | R47: 0.4 | S47: 0.4 | T47: 0.4 | U47: 0.4 | V47: 0.4 | W47: 0.4 | X47: 0.4 | Y47: 0.4 | Z47: 0.4 | AA47: 0.4 | AB47: 0.4 | AC47: 0.4
B48: =$B$16 -> Base Case | F48: 0.3 | G48: 0.3 | H48: 0.3 | I48: 0.3 | J48: 0.3 | K48: 0.3 | L48: 0.3 | M48: 0.3 | N48: 0.3 | O48: 0.3 | P48: 0.3 | Q48: 0.3 | R48: 0.1 | S48: 0.1 | T48: 0.1 | U48: 0.1 | V48: 0.1 | W48: 0.1 | X48: 0.1 | Y48: 0.1 | Z48: 0.1 | AA48: 0.1 | AB48: 0.1 | AC48: 0.1
B49: =$B$17 -> Worst Case | F49: 0 | G49: 0 | H49: 0 | I49: 0 | J49: 0 | K49: 0 | L49: 0 | M49: 0 | N49: 0 | O49: 0 | P49: 0 | Q49: 0 | R49: 0 | S49: 0 | T49: 0 | U49: 0 | V49: 0 | W49: 0 | X49: 0 | Y49: 0 | Z49: 0 | AA49: 0 | AB49: 0 | AC49: 0
B51: Customer Succes Hires | F51: {=INDEX(F53:F55,$D$8)} -> 0.5 | G51: {=INDEX(G53:G55,$D$8)} -> 0.5 | H51: {=INDEX(H53:H55,$D$8)} -> 0.5 | I51: {=INDEX(I53:I55,$D$8)} -> 0.5 | J51: {=INDEX(J53:J55,$D$8)} -> 0.5 | K51: {=INDEX(K53:K55,$D$8)} -> 0.5 | L51: {=INDEX(L53:L55,$D$8)} -> 0.5 | M51: {=INDEX(M53:M55,$D$8)} -> 0.5 | ... AC51: {=INDEX(AC53:AC55,$D$8)} -> 0.3
B53: =$B$15 -> Best Case | F53: 1 | G53: 1 | H53: 1 | I53: 1 | J53: 1 | K53: 1 | L53: 1 | M53: 1 | N53: 1 | O53: 1 | P53: 1 | Q53: 1 | R53: 1 | S53: 1 | T53: 1 | U53: 1 | V53: 1 | W53: 1 | X53: 1 | Y53: 1 | Z53: 1 | AA53: 1 | AB53: 1 | AC53: 1
B54: =$B$16 -> Base Case | F54: 0.5 | G54: 0.5 | H54: 0.5 | I54: 0.5 | J54: 0.5 | K54: 0.5 | L54: 0.5 | M54: 0.5 | N54: 0.5 | O54: 0.5 | P54: 0.5 | Q54: 0.5 | R54: 0.25 | S54: 0.3 | T54: 0.3 | U54: 0.3 | V54: 0.3 | W54: 0.3 | X54: 0.3 | Y54: 0.3 | Z54: 0.3 | AA54: 0.3 | AB54: 0.3 | AC54: 0.3
B55: =$B$17 -> Worst Case | F55: 0 | G55: 0 | H55: 0 | I55: 0 | J55: 0 | K55: 0 | L55: 0 | M55: 0 | N55: 0 | O55: 0 | P55: 0 | Q55: 0 | R55: 0 | S55: 0 | T55: 0 | U55: 0 | V55: 0 | W55: 0 | X55: 0 | Y55: 0 | Z55: 0 | AA55: 0 | AB55: 0 | AC55: 0
B57: Product Hires | F57: {=INDEX(F59:F61,$D$8)} -> 1 | G57: {=INDEX(G59:G61,$D$8)} -> 1 | H57: {=INDEX(H59:H61,$D$8)} -> 1 | I57: {=INDEX(I59:I61,$D$8)} -> 1 | J57: {=INDEX(J59:J61,$D$8)} -> 1 | K57: {=INDEX(K59:K61,$D$8)} -> 1 | L57: {=INDEX(L59:L61,$D$8)} -> 1 | M57: {=INDEX(M59:M61,$D$8)} -> 1 | ... AC57: {=INDEX(AC59:AC61,$D$8)} -> 0.5
B59: =$B$15 -> Best Case | F59: 2 | G59: 2 | H59: 2 | I59: 2 | J59: 2 | K59: 2 | L59: 2 | M59: 2 | N59: 2 | O59: 2 | P59: 2 | Q59: 2 | R59: 1.5 | S59: 1.5 | T59: 1.5 | U59: 1.5 | V59: 1.5 | W59: 1.5 | X59: 1.5 | Y59: 1.5 | Z59: 1.5 | AA59: 1.5 | AB59: 1.5 | AC59: 1.5
B60: =$B$16 -> Base Case | F60: 1 | G60: 1 | H60: 1 | I60: 1 | J60: 1 | K60: 1 | L60: 1 | M60: 1 | N60: 1 | O60: 1 | P60: 1 | Q60: 1 | R60: 0.5 | S60: 0.5 | T60: 0.5 | U60: 0.5 | V60: 0.5 | W60: 0.5 | X60: 0.5 | Y60: 0.5 | Z60: 0.5 | AA60: 0.5 | AB60: 0.5 | AC60: 0.5
B61: =$B$17 -> Worst Case | F61: 0 | G61: 0 | H61: 0 | I61: 0 | J61: 0 | K61: 0 | L61: 0 | M61: 0 | N61: 0 | O61: 0 | P61: 0 | Q61: 0 | R61: 0 | S61: 0 | T61: 0 | U61: 0 | V61: 0 | W61: 0 | X61: 0 | Y61: 0 | Z61: 0 | AA61: 0 | AB61: 0 | AC61: 0
B63: G&A Hires | F63: {=INDEX(F65:F67,$D$8)} -> 0.3 | G63: {=INDEX(G65:G67,$D$8)} -> 0.3 | H63: {=INDEX(H65:H67,$D$8)} -> 0.3 | I63: {=INDEX(I65:I67,$D$8)} -> 0.3 | J63: {=INDEX(J65:J67,$D$8)} -> 0.3 | K63: {=INDEX(K65:K67,$D$8)} -> 0.3 | L63: {=INDEX(L65:L67,$D$8)} -> 0.3 | M63: {=INDEX(M65:M67,$D$8)} -> 0.3 | ... AC63: {=INDEX(AC65:AC67,$D$8)} -> 0.1
B65: =$B$15 -> Best Case | F65: 1 | G65: 1 | H65: 1 | I65: 1 | J65: 1 | K65: 1 | L65: 1 | M65: 1 | N65: 1 | O65: 1 | P65: 1 | Q65: 1 | R65: 0.5 | S65: 0.5 | T65: 0.5 | U65: 0.5 | V65: 0.5 | W65: 0.5 | X65: 0.5 | Y65: 0.5 | Z65: 0.5 | AA65: 0.5 | AB65: 0.5 | AC65: 0.5
B66: =$B$16 -> Base Case | F66: 0.3 | G66: 0.3 | H66: 0.3 | I66: 0.3 | J66: 0.3 | K66: 0.3 | L66: 0.3 | M66: 0.3 | N66: 0.3 | O66: 0.3 | P66: 0.3 | Q66: 0.3 | R66: 0.1 | S66: 0.1 | T66: 0.1 | U66: 0.1 | V66: 0.1 | W66: 0.1 | X66: 0.1 | Y66: 0.1 | Z66: 0.1 | AA66: 0.1 | AB66: 0.1 | AC66: 0.1
B67: =$B$17 -> Worst Case | F67: 0 | G67: 0 | H67: 0 | I67: 0 | J67: 0 | K67: 0 | L67: 0 | M67: 0 | N67: 0 | O67: 0 | P67: 0 | Q67: 0 | R67: 0 | S67: 0 | T67: 0 | U67: 0 | V67: 0 | W67: 0 | X67: 0 | Y67: 0 | Z67: 0 | AA67: 0 | AB67: 0 | AC67: 0
B69: Payroll Tax | F69: 0.22 | G69: 0.22 | H69: 0.22 | I69: 0.22 | J69: 0.22 | K69: 0.22 | L69: 0.22 | M69: 0.22 | N69: 0.22 | O69: 0.22 | P69: 0.22 | Q69: 0.22 | R69: 0.22 | S69: 0.22 | T69: 0.22 | U69: 0.22 | V69: 0.22 | W69: 0.22 | X69: 0.22 | Y69: 0.22 | Z69: 0.22 | AA69: 0.22 | AB69: 0.22 | AC69: 0.22
B71: Salary AE | F71: 70 | G71: 70 | H71: 70 | I71: 70 | J71: 70 | K71: 70 | L71: 70 | M71: 70 | N71: 70 | O71: 70 | P71: 70 | Q71: 70 | R71: 70 | S71: 70 | T71: 70 | U71: 70 | V71: 70 | W71: 70 | X71: 70 | Y71: 70 | Z71: 70 | AA71: 70 | AB71: 70 | AC71: 70
B73: Salary SDR | F73: 45 | G73: 45 | H73: 45 | I73: 45 | J73: 45 | K73: 45 | L73: 45 | M73: 45 | N73: 45 | O73: 45 | P73: 45 | Q73: 45 | R73: 45 | S73: 45 | T73: 45 | U73: 45 | V73: 45 | W73: 45 | X73: 45 | Y73: 45 | Z73: 45 | AA73: 45 | AB73: 45 | AC73: 45
B75: Salary CSM | F75: 58 | G75: 58 | H75: 58 | I75: 58 | J75: 58 | K75: 58 | L75: 58 | M75: 58 | N75: 58 | O75: 58 | P75: 58 | Q75: 58 | R75: 58 | S75: 58 | T75: 58 | U75: 58 | V75: 58 | W75: 58 | X75: 58 | Y75: 58 | Z75: 58 | AA75: 58 | AB75: 58 | AC75: 58
B77: Salary Product | F77: 85 | G77: 85 | H77: 85 | I77: 85 | J77: 85 | K77: 85 | L77: 85 | M77: 85 | N77: 85 | O77: 85 | P77: 85 | Q77: 85 | R77: 85 | S77: 85 | T77: 85 | U77: 85 | V77: 85 | W77: 85 | X77: 85 | Y77: 85 | Z77: 85 | AA77: 85 | AB77: 85 | AC77: 85
B79: Salary G&A | F79: 65 | G79: 65 | H79: 65 | I79: 65 | J79: 65 | K79: 65 | L79: 65 | M79: 65 | N79: 65 | O79: 65 | P79: 65 | Q79: 65 | R79: 65 | S79: 65 | T79: 65 | U79: 65 | V79: 65 | W79: 65 | X79: 65 | Y79: 65 | Z79: 65 | AA79: 65 | AB79: 65 | AC79: 65
B81: Cost of Revenue Driver
B83: Hosting & Infrastructure (% ARR) | F83: {=INDEX(F85:F87,$D$8)} -> 0.05 | G83: {=INDEX(G85:G87,$D$8)} -> 0.05 | H83: {=INDEX(H85:H87,$D$8)} -> 0.05 | I83: {=INDEX(I85:I87,$D$8)} -> 0.05 | J83: {=INDEX(J85:J87,$D$8)} -> 0.05 | K83: {=INDEX(K85:K87,$D$8)} -> 0.05 | L83: {=INDEX(L85:L87,$D$8)} -> 0.05 | M83: {=INDEX(M85:M87,$D$8)} -> 0.05 | ... AC83: {=INDEX(AC85:AC87,$D$8)} -> 0.05
B85: =$B$15 -> Best Case | F85: 0.04 | G85: 0.04 | H85: 0.04 | I85: 0.04 | J85: 0.04 | K85: 0.04 | L85: 0.04 | M85: 0.04 | N85: 0.04 | O85: 0.04 | P85: 0.04 | Q85: 0.04 | R85: 0.04 | S85: 0.04 | T85: 0.04 | U85: 0.04 | V85: 0.04 | W85: 0.04 | X85: 0.04 | Y85: 0.04 | Z85: 0.04 | AA85: 0.04 | AB85: 0.04 | AC85: 0.04
B86: =$B$16 -> Base Case | F86: 0.05 | G86: 0.05 | H86: 0.05 | I86: 0.05 | J86: 0.05 | K86: 0.05 | L86: 0.05 | M86: 0.05 | N86: 0.05 | O86: 0.05 | P86: 0.05 | Q86: 0.05 | R86: 0.05 | S86: 0.05 | T86: 0.05 | U86: 0.05 | V86: 0.05 | W86: 0.05 | X86: 0.05 | Y86: 0.05 | Z86: 0.05 | AA86: 0.05 | AB86: 0.05 | AC86: 0.05
B87: =$B$17 -> Worst Case | F87: 0.07 | G87: 0.07 | H87: 0.07 | I87: 0.07 | J87: 0.07 | K87: 0.07 | L87: 0.07 | M87: 0.07 | N87: 0.07 | O87: 0.07 | P87: 0.07 | Q87: 0.07 | R87: 0.07 | S87: 0.07 | T87: 0.07 | U87: 0.07 | V87: 0.07 | W87: 0.07 | X87: 0.07 | Y87: 0.07 | Z87: 0.07 | AA87: 0.07 | AB87: 0.07 | AC87: 0.07
B89: OpEx Drivers
B91: Marketing Spend (% ARR) | F91: {=INDEX(F93:F95,$D$8)+'Operational Model'!$Q$551} -> 0.14 | G91: {=INDEX(G93:G95,$D$8)+'Operational Model'!$Q$551} -> 0.14 | H91: {=INDEX(H93:H95,$D$8)+'Operational Model'!$Q$551} -> 0.14 | I91: {=INDEX(I93:I95,$D$8)+'Operational Model'!$Q$551} -> 0.14 | J91: {=INDEX(J93:J95,$D$8)+'Operational Model'!$Q$551} -> 0.14 | K91: {=INDEX(K93:K95,$D$8)+'Operational Model'!$Q$551} -> 0.14 | L91: {=INDEX(L93:L95,$D$8)+'Operational Model'!$Q$551} -> 0.14 | M91: {=INDEX(M93:M95,$D$8)+'Operational Model'!$Q$551} -> 0.14 | ... AC91: {=INDEX(AC93:AC95,$D$8)+'Operational Model'!$Q$551} -> 0.13
B93: =$B$15 -> Best Case | F93: 0.12 | G93: 0.12 | H93: 0.12 | I93: 0.12 | J93: 0.12 | K93: 0.12 | L93: 0.12 | M93: 0.12 | N93: 0.12 | O93: 0.12 | P93: 0.12 | Q93: 0.12 | R93: 0.119 | S93: 0.118 | T93: 0.117 | U93: 0.116 | V93: 0.115 | W93: 0.114 | X93: 0.113 | Y93: 0.112 | Z93: 0.111 | AA93: 0.11 | AB93: 0.11 | AC93: 0.11
B94: =$B$16 -> Base Case | F94: 0.14 | G94: 0.14 | H94: 0.14 | I94: 0.14 | J94: 0.14 | K94: 0.14 | L94: 0.14 | M94: 0.14 | N94: 0.14 | O94: 0.14 | P94: 0.14 | Q94: 0.14 | R94: 0.139 | S94: 0.138 | T94: 0.137 | U94: 0.136 | V94: 0.135 | W94: 0.134 | X94: 0.133 | Y94: 0.132 | Z94: 0.131 | AA94: 0.13 | AB94: 0.13 | AC94: 0.13
B95: =$B$17 -> Worst Case | F95: 0.16 | G95: 0.16 | H95: 0.16 | I95: 0.16 | J95: 0.16 | K95: 0.16 | L95: 0.16 | M95: 0.16 | N95: 0.16 | O95: 0.16 | P95: 0.16 | Q95: 0.16 | R95: 0.159 | S95: 0.158 | T95: 0.157 | U95: 0.156 | V95: 0.155 | W95: 0.154 | X95: 0.153 | Y95: 0.152 | Z95: 0.151 | AA95: 0.15 | AB95: 0.15 | AC95: 0.15
B97: Non-Personnel G&A Spend (% ARR) | F97: {=INDEX(F99:F101,$D$8)} -> 0.1 | G97: {=INDEX(G99:G101,$D$8)} -> 0.1 | H97: {=INDEX(H99:H101,$D$8)} -> 0.1 | I97: {=INDEX(I99:I101,$D$8)} -> 0.1 | J97: {=INDEX(J99:J101,$D$8)} -> 0.1 | K97: {=INDEX(K99:K101,$D$8)} -> 0.1 | L97: {=INDEX(L99:L101,$D$8)} -> 0.1 | M97: {=INDEX(M99:M101,$D$8)} -> 0.1 | ... AC97: {=INDEX(AC99:AC101,$D$8)} -> 0.09
B99: =$B$15 -> Best Case | F99: 0.08 | G99: 0.08 | H99: 0.08 | I99: 0.08 | J99: 0.08 | K99: 0.08 | L99: 0.08 | M99: 0.08 | N99: 0.08 | O99: 0.08 | P99: 0.08 | Q99: 0.08 | R99: 0.079 | S99: 0.078 | T99: 0.077 | U99: 0.076 | V99: 0.075 | W99: 0.074 | X99: 0.073 | Y99: 0.072 | Z99: 0.071 | AA99: 0.07 | AB99: 0.07 | AC99: 0.07
B100: =$B$16 -> Base Case | F100: 0.1 | G100: 0.1 | H100: 0.1 | I100: 0.1 | J100: 0.1 | K100: 0.1 | L100: 0.1 | M100: 0.1 | N100: 0.1 | O100: 0.1 | P100: 0.1 | Q100: 0.1 | R100: 0.099 | S100: 0.098 | T100: 0.097 | U100: 0.096 | V100: 0.095 | W100: 0.094 | X100: 0.093 | Y100: 0.092 | Z100: 0.091 | AA100: 0.09 | AB100: 0.09 | AC100: 0.09
B101: =$B$17 -> Worst Case | F101: 0.13 | G101: 0.13 | H101: 0.13 | I101: 0.13 | J101: 0.13 | K101: 0.13 | L101: 0.13 | M101: 0.13 | N101: 0.13 | O101: 0.13 | P101: 0.13 | Q101: 0.13 | R101: 0.128 | S101: 0.126 | T101: 0.124 | U101: 0.122 | V101: 0.12 | W101: 0.118 | X101: 0.116 | Y101: 0.114 | Z101: 0.112 | AA101: 0.11 | AB101: 0.11 | AC101: 0.11
B103: CapEx Driver
B105: CapEx % of ARR | F105: 0.02 | G105: 0.02 | H105: 0.02 | I105: 0.02 | J105: 0.02 | K105: 0.02 | L105: 0.02 | M105: 0.02 | N105: 0.02 | O105: 0.02 | P105: 0.02 | Q105: 0.02 | R105: 0.018 | S105: 0.018 | T105: 0.018 | U105: 0.018 | V105: 0.018 | W105: 0.018 | X105: 0.018 | Y105: 0.018 | Z105: 0.018 | AA105: 0.018 | AB105: 0.018 | AC105: 0.018
B110: Funding Drivers | J110: Deferred Revenue Drivers | S110: Customer Acquisition Driver
B112: Minimum Runway Treshold (months) | F112: 18 | J112: Annual Prepaid Customers | O112: 0.6 | S112: Customer Acquisition % of S&M Expense | X112: 0.8
B113: Funding Amount | F113: 12000 | J113: Annual Contract Term | O113: 12
B114: Funding Round | F114: Series B | J114: Average Remaining Contract Months | O114: 5.5
B116: Working Capital Drivers | J116: PP&E & Depreciation Drivers
B118: Accounts Receivable Days | F118: 31 | J118: PP&E Useful Life | O118: 36
B119: Accounts Payable Days | F119: 45 | J119: Opening Net PP&E Remaining Life | O119: 36
B120: Accrued Expenses (% of relevant expenses) | F120: 0.05
B121: Prepaid Expenses (% of relevant expenses) | F121: 0.05
B125: Long-Term Valuation Assumptions
B127: All figures in EUR thousands unless stated
F129: 2028 | G129: =F129+1 -> 2029 | H129: =G129+1 -> 2030 | I129: =H129+1 -> 2031 | J129: =I129+1 -> 2032 | K129: =J129+1 -> 2033 | L129: =K129+1 -> 2034 | M129: =L129+1 -> 2035 | N129: Term. | Q129: Weighted Average Cost of Capital
B131: Valuation Assumptions
Z132: Debt/ | AA132: Debt/ | AB132: Levered | AC132: Unlev.
B133: Revenue Growth | F133: {=INDEX(F135:F137,$D$8)} -> 0.23 | G133: {=INDEX(G135:G137,$D$8)} -> 0.19 | H133: {=INDEX(H135:H137,$D$8)} -> 0.16 | I133: {=INDEX(I135:I137,$D$8)} -> 0.13 | J133: {=INDEX(J135:J137,$D$8)} -> 0.1 | K133: {=INDEX(K135:K137,$D$8)} -> 0.08 | L133: {=INDEX(L135:L137,$D$8)} -> 0.06 | M133: {=INDEX(M135:M137,$D$8)} -> 0.04 | N133: {=INDEX(N135:N137,$D$8)} -> 0.025 | Q133: Name | S133: Country | U133: Debt | W133: Equity | Y133: Tax Rate | Z133: Equity | AA133: Capital | AB133: Beta | AC133: Beta
B135: =$B$15 -> Best Case | F135: 0.38 | G135: 0.31 | H135: 0.25 | I135: 0.2 | J135: 0.16 | K135: 0.12 | L135: 0.09 | M135: 0.06 | N135: 0.025 | Q135: Qt Group | S135: Finland | U135: 20000 | V135: 600000 | Y135: 0.2 | Z135: =U135/V135 -> 0.033333333 | AA135: =U135/(U135+V135) -> 0.032258065 | AB135: 1.48 | AC135: =AB135/(1+(1-Y135)*Z135) -> 1.4415584
B136: =$B$16 -> Base Case | F136: 0.23 | G136: 0.19 | H136: 0.16 | I136: 0.13 | J136: 0.1 | K136: 0.08 | L136: 0.06 | M136: 0.04 | N136: 0.025 | Q136: Truecaller | S136: Sweden | U136: 0 | V136: 370000 | Y136: 0.206 | Z136: =U136/V136 -> 0 | AA136: =U136/(U136+V136) -> 0 | AB136: 1.18 | AC136: =AB136/(1+(1-Y136)*Z136) -> 1.18
B137: =$B$17 -> Worst Case | F137: 0.02 | G137: 0.04 | H137: 0.06 | I137: 0.07 | J137: 0.07 | K137: 0.06 | L137: 0.05 | M137: 0.04 | N137: 0.02 | Q137: Vitec Software | S137: Sweden | U137: 277000 | V137: 970000 | Y137: 0.206 | Z137: =U137/V137 -> 0.28556701 | AA137: =U137/(U137+V137) -> 0.22213312 | AB137: 0.85 | AC137: =AB137/(1+(1-Y137)*Z137) -> 0.69289324
Q138: TeamViewer | S138: Germany | U138: 942966 | V138: 920000 | Y138: 0.3 | Z138: =U138/V138 -> 1.024963 | AA138: =U138/(U138+V138) -> 0.50616383 | AB138: 1.01 | AC138: =AB138/(1+(1-Y138)*Z138) -> 0.5880729
B139: Gross Margin | F139: {=INDEX(F141:F143,$D$8)} -> 0.855 | G139: {=INDEX(G141:G143,$D$8)} -> 0.86 | H139: {=INDEX(H141:H143,$D$8)} -> 0.865 | I139: {=INDEX(I141:I143,$D$8)} -> 0.87 | J139: {=INDEX(J141:J143,$D$8)} -> 0.87 | K139: {=INDEX(K141:K143,$D$8)} -> 0.87 | L139: {=INDEX(L141:L143,$D$8)} -> 0.87 | M139: {=INDEX(M141:M143,$D$8)} -> 0.87 | N139: {=INDEX(N141:N143,$D$8)} -> 0.87 | Q139: Nemetschek | S139: Germany | U139: 400000 | V139: 10717000 | Y139: 0.3 | Z139: =U139/V139 -> 0.037323878 | AA139: =U139/(U139+V139) -> 0.03598093 | AB139: 0.54 | AC139: =AB139/(1+(1-Y139)*Z139) -> 0.5262508
Q140: Sinch | S140: Sweden | U140: 638300 | V140: 2033000 | Y140: 0.206 | Z140: =U140/V140 -> 0.3139695 | AA140: =U140/(U140+V140) -> 0.23894733 | AB140: 2.48 | AC140: =AB140/(1+(1-Y140)*Z140) -> 1.9851247
B141: =$B$15 -> Best Case | F141: 0.86 | G141: 0.868 | H141: 0.875 | I141: 0.88 | J141: 0.885 | K141: 0.89 | L141: 0.89 | M141: 0.89 | N141: 0.89
B142: =$B$16 -> Base Case | F142: 0.855 | G142: 0.86 | H142: 0.865 | I142: 0.87 | J142: 0.87 | K142: 0.87 | L142: 0.87 | M142: 0.87 | N142: 0.87 | X142: Average | Y142: =AVERAGE(Y135:Y140) -> 0.23633333 | Z142: =AVERAGE(Z135:Z140) -> 0.28252613 | AA142: =AVERAGE(AA135:AA140) -> 0.17258055 | AB142: =AVERAGE(AB135:AB140) -> 1.2566667 | AC142: =AVERAGE(AC135:AC140) -> 1.0689833
B143: =$B$17 -> Worst Case | F143: 0.83 | G143: 0.835 | H143: 0.84 | I143: 0.845 | J143: 0.85 | K143: 0.85 | L143: 0.85 | M143: 0.85 | N143: 0.85 | X143: Median | Y143: =MEDIAN(Y135:Y140) -> 0.206 | Z143: =MEDIAN(Z135:Z140) -> 0.16144544 | AA143: =MEDIAN(AA135:AA140) -> 0.12905702 | AB143: =MEDIAN(AB135:AB140) -> 1.095 | AC143: =MEDIAN(AC135:AC140) -> 0.93644662
B145: EBITDA Margin | F145: {=INDEX(F147:F149,$D$8)} -> 0.05 | G145: {=INDEX(G147:G149,$D$8)} -> 0.08 | H145: {=INDEX(H147:H149,$D$8)} -> 0.11 | I145: {=INDEX(I147:I149,$D$8)} -> 0.14 | J145: {=INDEX(J147:J149,$D$8)} -> 0.165 | K145: {=INDEX(K147:K149,$D$8)} -> 0.185 | L145: {=INDEX(L147:L149,$D$8)} -> 0.2 | M145: {=INDEX(M147:M149,$D$8)} -> 0.21 | N145: {=INDEX(N147:N149,$D$8)} -> 0.22
Q146: Risk Premium for Equity | X146: Cost of Equity
B147: =$B$15 -> Best Case | F147: 0.07 | G147: 0.11 | H147: 0.15 | I147: 0.18 | J147: 0.21 | K147: 0.23 | L147: 0.24 | M147: 0.25 | N147: 0.25
B148: =$B$16 -> Base Case | F148: 0.05 | G148: 0.08 | H148: 0.11 | I148: 0.14 | J148: 0.165 | K148: 0.185 | L148: 0.2 | M148: 0.21 | N148: 0.22 | Q148: Market Risk Premium | V148: 0.0423 | X148: Risk Free Rate | AC148: 0.0297
B149: =$B$17 -> Worst Case | F149: -0.07 | G149: -0.03 | H149: 0.01 | I149: 0.04 | J149: 0.07 | K149: 0.1 | L149: 0.12 | M149: 0.14 | N149: 0.15 | Q149: Median Unlevered Beta | V149: =AC143 -> 0.93644662 | X149: Equity Risk Premium | AC149: =V151 -> 0.043967004
Q150: Relevered Beta | V150: =V149*(1+(1-AC157)*V161) -> 1.0394091 | X150: Country Risk Premium | AC150: 0
B151: Depreciation % Revenue | F151: {=INDEX(F153:F155,$D$8)} -> 0.02 | G151: {=INDEX(G153:G155,$D$8)} -> 0.019 | H151: {=INDEX(H153:H155,$D$8)} -> 0.019 | I151: {=INDEX(I153:I155,$D$8)} -> 0.018 | J151: {=INDEX(J153:J155,$D$8)} -> 0.018 | K151: {=INDEX(K153:K155,$D$8)} -> 0.018 | L151: {=INDEX(L153:L155,$D$8)} -> 0.018 | M151: {=INDEX(M153:M155,$D$8)} -> 0.018 | N151: {=INDEX(N153:N155,$D$8)} -> 0.018 | Q151: Equity Risk Premium | V151: =V148*V150 -> 0.043967004 | X151: Size Premium | AC151: 0.0447
X152: Cost of Equity | AC152: =SUM(AC148:AC151) -> 0.118367
B153: =$B$15 -> Best Case | F153: 0.016 | G153: 0.016 | H153: 0.016 | I153: 0.016 | J153: 0.016 | K153: 0.016 | L153: 0.016 | M153: 0.016 | N153: 0.016
B154: =$B$16 -> Base Case | F154: 0.02 | G154: 0.019 | H154: 0.019 | I154: 0.018 | J154: 0.018 | K154: 0.018 | L154: 0.018 | M154: 0.018 | N154: 0.018 | Q154: Capital Structure | X154: Cost of Debt
...

Sheet Operational Model
B1: Gale Suer - Financial Analyst
B3: Income Statement
B5: All figures in EUR thousands unless stated | G5: =Inputs!F$7 -> 2026 | H5: =Inputs!G$7 -> 2026 | I5: =Inputs!H$7 -> 2026 | J5: =Inputs!I$7 -> 2026 | K5: =Inputs!J$7 -> 2026 | L5: =Inputs!K$7 -> 2026 | M5: =Inputs!L$7 -> 2026 | N5: =Inputs!M$7 -> 2026 | ... AD5: =Inputs!AC$7 -> 2027
B6: {=CONCATENATE("Model Running: ",INDEX(Inputs!$B$15:$B$17,Inputs!$D$8)," Drivers")} -> Model Running: Base Case Drivers | G6: =Inputs!F$8 -> 1 | H6: =Inputs!G$8 -> 1 | I6: =Inputs!H$8 -> 1 | J6: =Inputs!I$8 -> 2 | K6: =Inputs!J$8 -> 2 | L6: =Inputs!K$8 -> 2 | M6: =Inputs!L$8 -> 3 | N6: =Inputs!M$8 -> 3 | ... AD6: =Inputs!AC$8 -> 4
G7: =Inputs!F$9 -> 46053 | H7: =Inputs!G$9 -> 46081 | I7: =Inputs!H$9 -> 46112 | J7: =Inputs!I$9 -> 46142 | K7: =Inputs!J$9 -> 46173 | L7: =Inputs!K$9 -> 46203 | M7: =Inputs!L$9 -> 46234 | N7: =Inputs!M$9 -> 46265 | ... AD7: =Inputs!AC$9 -> 46752
B10: Revenue | G10: =G155 -> 913.2228 | H10: =H155 -> 933.64625 | I10: =I155 -> 953.82026 | J10: =J155 -> 973.79366 | K10: =K155 -> 993.61427 | L10: =L155 -> 1013.329 | M10: =M155 -> 1032.9839 | N10: =N155 -> 1052.6242 | ... AD10: =AD155 -> 1461.3423
B11: Cost of Revenue
B12: Customer Succes Personnel | G12: =-G279 -> -89.924167 | H12: =-H279 -> -92.8725 | I12: =-I279 -> -95.820833 | J12: =-J279 -> -98.769167 | K12: =-K279 -> -101.7175 | L12: =-L279 -> -104.66583 | M12: =-M279 -> -107.61417 | N12: =-N279 -> -110.5625 | ... AD12: =-AD279 -> -143.87867
B13: Hosting & Infrastructure | G13: =-G280 -> -45.66114 | H13: =-H280 -> -46.682313 | I13: =-I280 -> -47.691013 | J13: =-J280 -> -48.689683 | K13: =-K280 -> -49.680714 | L13: =-L280 -> -50.66645 | M13: =-M280 -> -51.649195 | N13: =-N280 -> -52.631209 | ... AD13: =-AD280 -> -73.067116
B14: Gross Profit | G14: =SUM(G10:G13) -> 777.63749 | H14: =SUM(H10:H13) -> 794.09144 | I14: =SUM(I10:I13) -> 810.30841 | J14: =SUM(J10:J13) -> 826.33481 | K14: =SUM(K10:K13) -> 842.21606 | L14: =SUM(L10:L13) -> 857.99672 | M14: =SUM(M10:M13) -> 873.72053 | N14: =SUM(N10:N13) -> 889.43047 | ... AD14: =SUM(AD10:AD13) -> 1244.3965
B16: Gross Margin | G16: =MAX(G14/G10,0) -> 0.85153097 | H16: =MAX(H14/H10,0) -> 0.8505271 | I16: =MAX(I14/I10,0) -> 0.84953995 | J16: =MAX(J14/J10,0) -> 0.8485728 | K16: =MAX(K14/K10,0) -> 0.84762879 | L16: =MAX(L14/L10,0) -> 0.84671091 | M16: =MAX(M14/M10,0) -> 0.84582203 | N16: =MAX(N14/N10,0) -> 0.84496489 | ... AD16: =MAX(AD14/AD10,0) -> 0.85154349
B19: Sales & Marketing | G19: =-G302 -> -309.96161 | H19: =-H302 -> -319.17506 | I19: =-I302 -> -328.35359 | J19: =-J302 -> -337.50403 | K19: =-K302 -> -346.63308 | L19: =-L302 -> -355.74731 | M19: =-M302 -> -364.85316 | N19: =-N302 -> -373.95697 | ... AD19: =-AD302 -> -483.15575
B20: R&D / Product | G20: =-G250 -> -306.77917 | H20: =-H250 -> -315.42083 | I20: =-I250 -> -324.0625 | J20: =-J250 -> -332.70417 | K20: =-K250 -> -341.34583 | L20: =-L250 -> -349.9875 | M20: =-M250 -> -358.62917 | N20: =-N250 -> -367.27083 | ... AD20: =-AD250 -> -455.84792
B21: G&A | G21: =-G303 -> -204.6552 | H21: =-H303 -> -208.68004 | I21: =-I303 -> -212.67994 | J21: =-J303 -> -216.65978 | K21: =-K303 -> -220.62434 | L21: =-L303 -> -224.57832 | M21: =-M303 -> -228.52631 | N21: =-N303 -> -232.47283 | ... AD21: =-AD303 -> -275.25206
B22: EBITDA | G22: =G14+SUM(G19:G21) -> -43.758479 | H22: =H14+SUM(H19:H21) -> -49.184495 | I22: =I14+SUM(I19:I21) -> -54.787615 | J22: =J14+SUM(J19:J21) -> -60.533169 | K22: =K14+SUM(K19:K21) -> -66.387198 | L22: =L14+SUM(L19:L21) -> -72.316406 | M22: =M14+SUM(M19:M21) -> -78.288105 | N22: =N14+SUM(N19:N21) -> -84.270165 | ... AD22: =AD14+SUM(AD19:AD21) -> 30.140804
B24: EBITDA Margin | G24: =G22/G10 -> -0.047916542 | H24: =H22/H10 -> -0.052680011 | I24: =I22/I10 -> -0.057440188 | J24: =J22/J10 -> -0.062162213 | K24: =K22/K10 -> -0.066813853 | L24: =L22/L10 -> -0.07136518 | M24: =M22/M10 -> -0.075788311 | N24: =N22/N10 -> -0.080057219 | ... AD24: =AD22/AD10 -> 0.020625423
B27: Depreciation | G27: =-G451 -> -15.785124 | H27: =-H451 -> -16.303816 | I27: =-I451 -> -16.833716 | J27: =-J451 -> -17.374713 | K27: =-K451 -> -17.926721 | L27: =-L451 -> -18.489681 | M27: =-M451 -> -19.063561 | N27: =-N451 -> -19.648352 | ... AD27: =-AD451 -> -29.932065
B28: EBIT | G28: =G22+G27 -> -59.543602 | H28: =H22+H27 -> -65.488311 | I28: =I22+I27 -> -71.621331 | J28: =J22+J27 -> -77.907881 | K28: =K22+K27 -> -84.313919 | L28: =L22+L27 -> -90.806088 | M28: =M22+M27 -> -97.351666 | N28: =N22+N27 -> -103.91852 | ... AD28: =AD22+AD27 -> 0.2087393
B31: Interest Income | G31: =G329*Inputs!$E$210/12 -> 8.0208333 | H31: =H329*Inputs!$E$210/12 -> 8.029714 | I31: =I329*Inputs!$E$210/12 -> 8.0218887 | J31: =J329*Inputs!$E$210/12 -> 8.000132 | K31: =K329*Inputs!$E$210/12 -> 7.9644008 | L31: =L329*Inputs!$E$210/12 -> 7.9147151 | M31: =M329*Inputs!$E$210/12 -> 7.851157 | N31: =N329*Inputs!$E$210/12 -> 7.7738703 | ... AD31: =AD329*Inputs!$E$210/12 -> 7.4299032
B32: EBT | G32: =G28+G31 -> -51.522769 | H32: =H28+H31 -> -57.458597 | I32: =I28+I31 -> -63.599442 | J32: =J28+J31 -> -69.907749 | K32: =K28+K31 -> -76.349518 | L32: =L28+L31 -> -82.891373 | M32: =M28+M31 -> -89.500509 | N32: =N28+N31 -> -96.144647 | ... AD32: =AD28+AD31 -> 7.6386425
B35: Current Tax | G35: =-MAX(G32*Inputs!$E$209,0) -> 0 | H35: =-MAX(H32*Inputs!$E$209,0) -> 0 | I35: =-MAX(I32*Inputs!$E$209,0) -> 0 | J35: =-MAX(J32*Inputs!$E$209,0) -> 0 | K35: =-MAX(K32*Inputs!$E$209,0) -> 0 | L35: =-MAX(L32*Inputs!$E$209,0) -> 0 | M35: =-MAX(M32*Inputs!$E$209,0) -> 0 | N35: =-MAX(N32*Inputs!$E$209,0) -> 0 | ... AD35: =-MAX(AD32*Inputs!$E$209,0) -> -1.9707698
B38: Net Income | G38: =G32+G35 -> -51.522769 | H38: =H32+H35 -> -57.458597 | I38: =I32+I35 -> -63.599442 | J38: =J32+J35 -> -69.907749 | K38: =K32+K35 -> -76.349518 | L38: =L32+L35 -> -82.891373 | M38: =M32+M35 -> -89.500509 | N38: =N32+N35 -> -96.144647 | ... AD38: =AD32+AD35 -> 5.6678728
B42: Cash Flow Statement
B44: All figures in EUR thousands unless stated | G44: =G$5 -> 2026 | H44: =H$5 -> 2026 | I44: =I$5 -> 2026 | J44: =J$5 -> 2026 | K44: =K$5 -> 2026 | L44: =L$5 -> 2026 | M44: =M$5 -> 2026 | N44: =N$5 -> 2026 | ... AD44: =AD$5 -> 2027
B45: {=CONCATENATE("Model Running: ",INDEX(Inputs!$B$15:$B$17,Inputs!$D$8)," Drivers")} -> Model Running: Base Case Drivers | G45: =G$6 -> 1 | H45: =H$6 -> 1 | I45: =I$6 -> 1 | J45: =J$6 -> 2 | K45: =K$6 -> 2 | L45: =L$6 -> 2 | M45: =M$6 -> 3 | N45: =N$6 -> 3 | ... AD45: =AD$6 -> 4
G46: =G$7 -> 46053 | H46: =H$7 -> 46081 | I46: =I$7 -> 46112 | J46: =J$7 -> 46142 | K46: =K$7 -> 46173 | L46: =L$7 -> 46203 | M46: =M$7 -> 46234 | N46: =N$7 -> 46265 | ... AD46: =AD$7 -> 46752
B49: Cash From Operating Activities
B50: Net Income | G50: =G38 -> -51.522769 | H50: =H38 -> -57.458597 | I50: =I38 -> -63.599442 | J50: =J38 -> -69.907749 | K50: =K38 -> -76.349518 | L50: =L38 -> -82.891373 | M50: =M38 -> -89.500509 | N50: =N38 -> -96.144647 | ... AD50: =AD38 -> 5.6678728
B51: Depreciation | G51: =-G27 -> 15.785124 | H51: =-H27 -> 16.303816 | I51: =-I27 -> 16.833716 | J51: =-J27 -> 17.374713 | K51: =-K27 -> 17.926721 | L51: =-L27 -> 18.489681 | M51: =-M27 -> 19.063561 | N51: =-N27 -> 19.648352 | ... AD51: =-AD27 -> 29.932065
B52: Changes in Working Capital
B53: Change in Accounts Receivable | G53: =-G387 -> -21.66356 | H53: =-H387 -> -21.104233 | I53: =-I387 -> -20.846477 | J53: =-J387 -> -20.639179 | K53: =-K387 -> -20.481303 | L53: =-L387 -> -20.371888 | M53: =-M387 -> -20.310048 | N53: =-N387 -> -20.294967 | ... AD53: =-AD387 -> -30.887425
B54: Change in Accounts Payable | G54: =G388 -> 12.251918 | H54: =H388 -> 8.8842012 | I54: =I388 -> 8.7756942 | J54: =J388 -> 8.6884284 | K54: =K388 -> 8.6219677 | L54: =L388 -> 8.5759077 | M54: =M388 -> 8.549875 | N54: =N388 -> 8.5435265 | ... AD54: =AD388 -> 12.105878
B55: Change in Accrued Expenses | G55: =G389 -> 0.60733333 | H55: =H389 -> 0.99633333 | I55: =I389 -> 0.99633333 | J55: =J389 -> 0.99633333 | K55: =K389 -> 0.99633333 | L55: =L389 -> 0.99633333 | M55: =M389 -> 0.99633333 | N55: =N389 -> 0.99633333 | ... AD55: =AD389 -> 0.50274167
B56: Change in Prepaid Expenses | G56: =-G390 -> 0.433886 | H56: =-H390 -> -0.10211726 | I56: =-I390 -> -0.10087005 | J56: =-J390 -> -0.099866993 | K56: =-K390 -> -0.099103077 | L56: =-L390 -> -0.098573651 | M56: =-M390 -> -0.098274425 | N56: =-N390 -> -0.098201454 | ... AD56: =-AD390 -> -0.13450975
B57: Change in Deferred Revenue | G57: =G414 -> 66.63524 | H57: =H414 -> 67.397388 | I57: =I414 -> 66.574232 | J57: =J414 -> 65.912215 | K57: =K414 -> 65.408031 | L57: =L414 -> 65.05861 | M57: =M414 -> 64.861121 | N57: =N414 -> 64.812959 | ... AD57: =AD414 -> 98.640486
B58: Subtotal | G58: =SUM(G50:G57) -> 22.527172 | H58: =SUM(H50:H57) -> 14.916792 | I58: =SUM(I50:I57) -> 8.6331867 | J58: =SUM(J50:J57) -> 2.3248952 | K58: =SUM(K50:K57) -> -3.9768714 | L58: =SUM(L50:L57) -> -10.241302 | M58: =SUM(M50:M57) -> -16.437941 | N58: =SUM(N50:N57) -> -22.536644 | ... AD58: =SUM(AD50:AD57) -> 115.82711
B61: Cash From Investing Activities
B62: Capital Expenditure | G62: =-G441 -> -18.264456 | H62: =-H441 -> -18.672925 | I62: =-I441 -> -19.076405 | J62: =-J441 -> -19.475873 | K62: =-K441 -> -19.872285 | L62: =-L441 -> -20.26658 | M62: =-M441 -> -20.659678 | N62: =-N441 -> -21.052484 | ... AD62: =-AD441 -> -26.304162
B63: Subtotal | G63: =G62 -> -18.264456 | H63: =H62 -> -18.672925 | I63: =I62 -> -19.076405 | J63: =J62 -> -19.475873 | K63: =K62 -> -19.872285 | L63: =L62 -> -20.26658 | M63: =M62 -> -20.659678 | N63: =N62 -> -21.052484 | ... AD63: =AD62 -> -26.304162
B66: Cash From Financing
B67: Change in Share Capital / APIC | G67: =G482 -> 0 | H67: =H482 -> 0 | I67: =I482 -> 0 | J67: =J482 -> 0 | K67: =K482 -> 0 | L67: =L482 -> 0 | M67: =M482 -> 0 | N67: =N482 -> 0 | ... AD67: =AD482 -> 0
B68: Dividends | G68: =G488 -> 0 | H68: =H488 -> 0 | I68: =I488 -> 0 | J68: =J488 -> 0 | K68: =K488 -> 0 | L68: =L488 -> 0 | M68: =M488 -> 0 | N68: =N488 -> 0 | ... AD68: =AD488 -> 0
B69: Subtotal | G69: =SUM(G67:G68) -> 0 | H69: =SUM(H67:H68) -> 0 | I69: =SUM(I67:I68) -> 0 | J69: =SUM(J67:J68) -> 0 | K69: =SUM(K67:K68) -> 0 | L69: =SUM(L67:L68) -> 0 | M69: =SUM(M67:M68) -> 0 | N69: =SUM(N67:N68) -> 0 | ... AD69: =SUM(AD67:AD68) -> 0
B72: Cash Balance
B73: Beginning | G73: =IF(Inputs!E183>0,Inputs!E183,'Operational Model'!F75) -> 3850 | H73: =IF(Inputs!F183>0,Inputs!F183,'Operational Model'!G75) -> 3854.2627 | I73: =IF(Inputs!G183>0,Inputs!G183,'Operational Model'!H75) -> 3850.5066 | J73: =IF(Inputs!H183>0,Inputs!H183,'Operational Model'!I75) -> 3840.0634 | K73: =IF(Inputs!I183>0,Inputs!I183,'Operational Model'!J75) -> 3822.9124 | L73: =IF(Inputs!J183>0,Inputs!J183,'Operational Model'!K75) -> 3799.0632 | M73: =IF(Inputs!K183>0,Inputs!K183,'Operational Model'!L75) -> 3768.5553 | N73: =IF(Inputs!L183>0,Inputs!L183,'Operational Model'!M75) -> 3731.4577 | ... AD73: =IF(Inputs!AB183>0,Inputs!AB183,'Operational Model'!AC75) -> 3566.3536
B74: Change in Cash | G74: =G58+G63+G69 -> 4.262716 | H74: =H58+H63+H69 -> -3.7561331 | I74: =I58+I63+I69 -> -10.443219 | J74: =J58+J63+J69 -> -17.150978 | K74: =K58+K63+K69 -> -23.849157 | L74: =L58+L63+L69 -> -30.507882 | M74: =M58+M63+M69 -> -37.097619 | N74: =N58+N63+N69 -> -43.589128 | ... AD74: =AD58+AD63+AD69 -> 89.522946
B75: Ending | G75: =SUM(G73:G74) -> 3854.2627 | H75: =SUM(H73:H74) -> 3850.5066 | I75: =SUM(I73:I74) -> 3840.0634 | J75: =SUM(J73:J74) -> 3822.9124 | K75: =SUM(K73:K74) -> 3799.0632 | L75: =SUM(L73:L74) -> 3768.5553 | M75: =SUM(M73:M74) -> 3731.4577 | N75: =SUM(N73:N74) -> 3687.8686 | ... AD75: =SUM(AD73:AD74) -> 3655.8765
B77: Model Integrity Check
B78: Cash Balance Check | G78: =IF(G73+G74=G75,0,1) -> 0 | H78: =IF(H73+H74=H75,0,1) -> 0 | I78: =IF(I73+I74=I75,0,1) -> 0 | J78: =IF(J73+J74=J75,0,1) -> 0 | K78: =IF(K73+K74=K75,0,1) -> 0 | L78: =IF(L73+L74=L75,0,1) -> 0 | M78: =IF(M73+M74=M75,0,1) -> 0 | N78: =IF(N73+N74=N75,0,1) -> 0 | ... AD78: =IF(AD73+AD74=AD75,0,1) -> 0
B82: Balance Sheet
B84: All figures in EUR thousands unless stated | G84: =G$5 -> 2026 | H84: =H$5 -> 2026 | I84: =I$5 -> 2026 | J84: =J$5 -> 2026 | K84: =K$5 -> 2026 | L84: =L$5 -> 2026 | M84: =M$5 -> 2026 | N84: =N$5 -> 2026 | ... AD84: =AD$5 -> 2027
B85: {=CONCATENATE("Model Running: ",INDEX(Inputs!$B$15:$B$17,Inputs!$D$8)," Drivers")} -> Model Running: Base Case Drivers | G85: =G$6 -> 1 | H85: =H$6 -> 1 | I85: =I$6 -> 1 | J85: =J$6 -> 2 | K85: =K$6 -> 2 | L85: =L$6 -> 2 | M85: =M$6 -> 3 | N85: =N$6 -> 3 | ... AD85: =AD$6 -> 4
G86: =G$7 -> 46053 | H86: =H$7 -> 46081 | I86: =I$7 -> 46112 | J86: =J$7 -> 46142 | K86: =K$7 -> 46173 | L86: =L$7 -> 46203 | M86: =M$7 -> 46234 | N86: =N$7 -> 46265 | ... AD86: =AD$7 -> 46752
B88: ASSETS
B90: Cash | G90: =G75 -> 3854.2627 | H90: =H75 -> 3850.5066 | I90: =I75 -> 3840.0634 | J90: =J75 -> 3822.9124 | K90: =K75 -> 3799.0632 | L90: =L75 -> 3768.5553 | M90: =M75 -> 3731.4577 | N90: =N75 -> 3687.8686 | ... AD90: =AD75 -> 3655.8765
B91: Accounts Receivable | G91: =G381 -> 943.66356 | H91: =H381 -> 964.76779 | I91: =I381 -> 985.61427 | J91: =J381 -> 1006.2534 | K91: =K381 -> 1026.7348 | L91: =L381 -> 1047.1066 | M91: =M381 -> 1067.4167 | N91: =N381 -> 1087.7117 | ... AD91: =AD381 -> 1510.0537
B92: Prepaid Expenses | G92: =G384 -> 4.566114 | H92: =H384 -> 4.6682313 | I92: =I384 -> 4.7691013 | J92: =J384 -> 4.8689683 | K92: =K384 -> 4.9680714 | L92: =L384 -> 5.066645 | M92: =M384 -> 5.1649195 | N92: =N384 -> 5.2631209 | ... AD92: =AD384 -> 6.5760404
B93: Total Current Assets | G93: =SUM(G90:G92) -> 4802.4924 | H93: =SUM(H90:H92) -> 4819.9426 | I93: =SUM(I90:I92) -> 4830.4467 | J93: =SUM(J90:J92) -> 4834.0348 | K93: =SUM(K90:K92) -> 4830.7661 | L93: =SUM(L90:L92) -> 4820.7286 | M93: =SUM(M90:M92) -> 4804.0393 | N93: =SUM(N90:N92) -> 4780.8434 | ... AD93: =SUM(AD90:AD92) -> 5172.5063
B95: Property Plant & Equipment | G95: =G461 -> 552.47933 | H95: =H461 -> 554.84844 | I95: =I461 -> 557.09113 | J95: =J461 -> 559.19229 | K95: =K461 -> 561.13786 | L95: =L461 -> 562.91475 | M95: =M461 -> 564.51087 | N95: =N461 -> 565.915 | ... AD95: =AD461 -> 537.34474
B97: Total Assets | G97: =G95+G93 -> 5354.9717 | H97: =H95+H93 -> 5374.791 | I97: =I95+I93 -> 5387.5379 | J97: =J95+J93 -> 5393.2271 | K97: =K95+K93 -> 5391.9039 | L97: =L95+L93 -> 5383.6434 | M97: =M95+M93 -> 5368.5502 | N97: =N95+N93 -> 5346.7584 | ... AD97: =AD95+AD93 -> 5709.851
B100: LIABILITIES
B102: Accounts Payable | G102: =G382 -> 397.25192 | H102: =H382 -> 406.13612 | I102: =I382 -> 414.91181 | J102: =J382 -> 423.60024 | K102: =K382 -> 432.22221 | L102: =L382 -> 440.79812 | M102: =M382 -> 449.34799 | N102: =N382 -> 457.89152 | ... AD102: =AD382 -> 591.84364
B103: Accrued Expenses | G103: =G383 -> 34.607333 | H103: =H383 -> 35.603667 | I103: =I383 -> 36.6 | J103: =J383 -> 37.596333 | K103: =K383 -> 38.592667 | L103: =L383 -> 39.589 | M103: =M383 -> 40.585333 | N103: =N383 -> 41.581667 | ... AD103: =AD383 -> 51.831954
B104: Deferred Revenue | G104: =G412 -> 3013.6352 | H104: =H412 -> 3081.0326 | I104: =I412 -> 3147.6069 | J104: =J412 -> 3213.5191 | K104: =K412 -> 3278.9271 | L104: =L412 -> 3343.9857 | M104: =M412 -> 3408.8468 | N104: =N412 -> 3473.6598 | ... AD104: =AD412 -> 4822.4296
B105: Total Liabilities | G105: =SUM(G102:G104) -> 3445.4945 | H105: =SUM(H102:H104) -> 3522.7724 | I105: =SUM(I102:I104) -> 3599.1187 | J105: =SUM(J102:J104) -> 3674.7157 | K105: =SUM(K102:K104) -> 3749.742 | L105: =SUM(L102:L104) -> 3824.3728 | M105: =SUM(M102:M104) -> 3898.7802 | N105: =SUM(N102:N104) -> 3973.133 | ... AD105: =SUM(AD102:AD104) -> 5466.1052
B108: EQUITY
B110: Share Capital / APIC | G110: =G483 -> 8000 | H110: =H483 -> 8000 | I110: =I483 -> 8000 | J110: =J483 -> 8000 | K110: =K483 -> 8000 | L110: =L483 -> 8000 | M110: =M483 -> 8000 | N110: =N483 -> 8000 | ... AD110: =AD483 -> 8000
B111: Retained Earnings | G111: =G489 -> -6090.5228 | H111: =H489 -> -6147.9814 | I111: =I489 -> -6211.5808 | J111: =J489 -> -6281.4886 | K111: =K489 -> -6357.8381 | L111: =L489 -> -6440.7294 | M111: =M489 -> -6530.23 | N111: =N489 -> -6626.3746 | ... AD111: =AD489 -> -7756.2542
B112: Total Shareholders' Equity | G112: =SUM(G110:G111) -> 1909.4772 | H112: =SUM(H110:H111) -> 1852.0186 | I112: =SUM(I110:I111) -> 1788.4192 | J112: =SUM(J110:J111) -> 1718.5114 | K112: =SUM(K110:K111) -> 1642.1619 | L112: =SUM(L110:L111) -> 1559.2706 | M112: =SUM(M110:M111) -> 1469.77 | N112: =SUM(N110:N111) -> 1373.6254 | ... AD112: =SUM(AD110:AD111) -> 243.74579
B115: Total Liabilities & Equity | G115: =G105+G112 -> 5354.9717 | H115: =H105+H112 -> 5374.791 | I115: =I105+I112 -> 5387.5379 | J115: =J105+J112 -> 5393.2271 | K115: =K105+K112 -> 5391.9039 | L115: =L105+L112 -> 5383.6434 | M115: =M105+M112 -> 5368.5502 | N115: =N105+N112 -> 5346.7584 | ... AD115: =AD105+AD112 -> 5709.851
B118: Check | G118: =IF(ABS(G97-G115)<0.001,0,G97-G115) -> 0 | H118: =IF(ABS(H97-H115)<0.001,0,H97-H115) -> 0 | I118: =IF(ABS(I97-I115)<0.001,0,I97-I115) -> 0 | J118: =IF(ABS(J97-J115)<0.001,0,J97-J115) -> 0 | K118: =IF(ABS(K97-K115)<0.001,0,K97-K115) -> 0 | L118: =IF(ABS(L97-L115)<0.001,0,L97-L115) -> 0 | M118: =IF(ABS(M97-M115)<0.001,0,M97-M115) -> 0 | N118: =IF(ABS(N97-N115)<0.001,0,N97-N115) -> 0 | ... AD118: =IF(ABS(AD97-AD115)<0.001,0,AD97-AD115) -> 0
B122: Revenue Forecast
B124: All figures in EUR thousands unless stated | G124: =G$5 -> 2026 | H124: =H$5 -> 2026 | I124: =I$5 -> 2026 | J124: =J$5 -> 2026 | K124: =K$5 -> 2026 | L124: =L$5 -> 2026 | M124: =M$5 -> 2026 | N124: =N$5 -> 2026 | ... AD124: =AD$5 -> 2027
B125: {=CONCATENATE("Model Running: ",INDEX(Inputs!$B$15:$B$17,Inputs!$D$8)," Drivers")} -> Model Running: Base Case Drivers | G125: =G$6 -> 1 | H125: =H$6 -> 1 | I125: =I$6 -> 1 | J125: =J$6 -> 2 | K125: =K$6 -> 2 | L125: =L$6 -> 2 | M125: =M$6 -> 3 | N125: =N$6 -> 3 | ... AD125: =AD$6 -> 4
G126: =G$7 -> 46053 | H126: =H$7 -> 46081 | I126: =I$7 -> 46112 | J126: =J$7 -> 46142 | K126: =K$7 -> 46173 | L126: =L$7 -> 46203 | M126: =M$7 -> 46234 | N126: =N$7 -> 46265 | ... AD126: =AD$7 -> 46752
B128: Lead Schedule | E128: (total #)
B129: Beginning | G129: =IF(Inputs!E177>0,Inputs!E177,'Operational Model'!F132) -> 875 | H129: =IF(Inputs!F177>0,Inputs!F177,'Operational Model'!G132) -> 875.02 | I129: =IF(Inputs!G177>0,Inputs!G177,'Operational Model'!H132) -> 876.0898 | J129: =IF(Inputs!H177>0,Inputs!H177,'Operational Model'!I132) -> 878.19893 | K129: =IF(Inputs!I177>0,Inputs!I177,'Operational Model'!J132) -> 881.33827 | L129: =IF(Inputs!J177>0,Inputs!J177,'Operational Model'!K132) -> 885.50006 | M129: =IF(Inputs!K177>0,Inputs!K177,'Operational Model'!L132) -> 890.67783 | N129: =IF(Inputs!L177>0,Inputs!L177,'Operational Model'!M132) -> 896.86643 | ... AD129: =IF(Inputs!AB177>0,Inputs!AB177,'Operational Model'!AC132) -> 1098.5999
B130: New Leads (marketing/sales) | G130: =IF(Inputs!E178>0,Inputs!E178*(1+Inputs!F13),'Operational Model'!F130*(1+Inputs!F13)) -> 35.02 | H130: =IF(Inputs!F178>0,Inputs!F178*(1+Inputs!G13),'Operational Model'!G130*(1+Inputs!G13)) -> 36.0706 | I130: =IF(Inputs!G178>0,Inputs!G178*(1+Inputs!H13),'Operational Model'!H130*(1+Inputs!H13)) -> 37.152718 | J130: =IF(Inputs!H178>0,Inputs!H178*(1+Inputs!I13),'Operational Model'!I130*(1+Inputs!I13)) -> 38.2673 | K130: =IF(Inputs!I178>0,Inputs!I178*(1+Inputs!J13),'Operational Model'!J130*(1+Inputs!J13)) -> 39.415319 | L130: =IF(Inputs!J178>0,Inputs!J178*(1+Inputs!K13),'Operational Model'!K130*(1+Inputs!K13)) -> 40.597778 | M130: =IF(Inputs!K178>0,Inputs!K178*(1+Inputs!L13),'Operational Model'!L130*(1+Inputs!L13)) -> 41.815711 | N130: =IF(Inputs!L178>0,Inputs!L178*(1+Inputs!M13),'Operational Model'!M130*(1+Inputs!M13)) -> 43.070183 | ... AD130: =IF(Inputs!AB178>0,Inputs!AB178*(1+Inputs!AC13),'Operational Model'!AC130*(1+Inputs!AC13)) -> 65.194656
B131: Converted Leads | G131: =-G129*Inputs!F$19 -> -35 | H131: =-H129*Inputs!G$19 -> -35.0008 | I131: =-I129*Inputs!H$19 -> -35.043592 | J131: =-J129*Inputs!I$19 -> -35.127957 | K131: =-K129*Inputs!J$19 -> -35.253531 | L131: =-L129*Inputs!K$19 -> -35.420002 | M131: =-M129*Inputs!L$19 -> -35.627113 | N131: =-N129*Inputs!M$19 -> -35.874657 | ... AD131: =-AD129*Inputs!AC$19 -> -46.141196
B132: Ending | G132: =SUM(G129:G131) -> 875.02 | H132: =SUM(H129:H131) -> 876.0898 | I132: =SUM(I129:I131) -> 878.19893 | J132: =SUM(J129:J131) -> 881.33827 | K132: =SUM(K129:K131) -> 885.50006 | L132: =SUM(L129:L131) -> 890.67783 | M132: =SUM(M129:M131) -> 896.86643 | N132: =SUM(N129:N131) -> 904.06196 | ... AD132: =SUM(AD129:AD131) -> 1117.6534
B134: Customer Roll-Forward | E134: (total #)
B135: Beginning | G135: =IF(Inputs!E179>0,Inputs!E179,'Operational Model'!F138) -> 850 | H135: =IF(Inputs!F179>0,Inputs!F179,'Operational Model'!G138) -> 868 | I135: =IF(Inputs!G179>0,Inputs!G179,'Operational Model'!H138) -> 885.6408 | J135: =IF(Inputs!H179>0,Inputs!H179,'Operational Model'!I138) -> 902.97158 | K135: =IF(Inputs!I179>0,Inputs!I179,'Operational Model'!J138) -> 920.0401 | L135: =IF(Inputs!J179>0,Inputs!J179,'Operational Model'!K138) -> 936.89283 | M135: =IF(Inputs!K179>0,Inputs!K179,'Operational Model'!L138) -> 953.57498 | N135: =IF(Inputs!L179>0,Inputs!L179,'Operational Model'!M138) -> 970.13059 | ... AD135: =IF(Inputs!AB179>0,Inputs!AB179,'Operational Model'!AC138) -> 1287.8472
B136: New Customers | G136: =-G131 -> 35 | H136: =-H131 -> 35.0008 | I136: =-I131 -> 35.043592 | J136: =-J131 -> 35.127957 | K136: =-K131 -> 35.253531 | L136: =-L131 -> 35.420002 | M136: =-M131 -> 35.627113 | N136: =-N131 -> 35.874657 | ... AD136: =-AD131 -> 46.141196
B137: Lost customers | G137: =-G135*Inputs!F31 -> -17 | H137: =-H135*Inputs!G31 -> -17.36 | I137: =-I135*Inputs!H31 -> -17.712816 | J137: =-J135*Inputs!I31 -> -18.059432 | K137: =-K135*Inputs!J31 -> -18.400802 | L137: =-L135*Inputs!K31 -> -18.737857 | M137: =-M135*Inputs!L31 -> -19.0715 | N137: =-N135*Inputs!M31 -> -19.402612 | ... AD137: =-AD135*Inputs!AC31 -> -23.18125
B138: Ending | G138: =SUM(G135:G137) -> 868 | H138: =SUM(H135:H137) -> 885.6408 | I138: =SUM(I135:I137) -> 902.97158 | J138: =SUM(J135:J137) -> 920.0401 | K138: =SUM(K135:K137) -> 936.89283 | L138: =SUM(L135:L137) -> 953.57498 | M138: =SUM(M135:M137) -> 970.13059 | N138: =SUM(N135:N137) -> 986.60264 | ... AD138: =SUM(AD135:AD137) -> 1310.8072
B140: ARPU Schedule | E140: (eur/user)
B141: Beginning | G141: =IF(Inputs!E180>0,Inputs!E180,'Operational Model'!F143) -> 1050 | H141: =IF(Inputs!F180>0,Inputs!F180,'Operational Model'!G143) -> 1052.1 | I141: =IF(Inputs!G180>0,Inputs!G180,'Operational Model'!H143) -> 1054.2042 | J141: =IF(Inputs!H180>0,Inputs!H180,'Operational Model'!I143) -> 1056.3126 | K141: =IF(Inputs!I180>0,Inputs!I180,'Operational Model'!J143) -> 1058.4252 | L141: =IF(Inputs!J180>0,Inputs!J180,'Operational Model'!K143) -> 1060.5421 | M141: =IF(Inputs!K180>0,Inputs!K180,'Operational Model'!L143) -> 1062.6632 | N141: =IF(Inputs!L180>0,Inputs!L180,'Operational Model'!M143) -> 1064.7885 | ... AD141: =IF(Inputs!AB180>0,Inputs!AB180,'Operational Model'!AC143) -> 1111.507
B142: Monthly ARPU | G142: =G141*Inputs!F25 -> 2.1 | H142: =H141*Inputs!G25 -> 2.1042 | I142: =I141*Inputs!H25 -> 2.1084084 | J142: =J141*Inputs!I25 -> 2.1126252 | K142: =K141*Inputs!J25 -> 2.1168505 | L142: =L141*Inputs!K25 -> 2.1210842 | M142: =M141*Inputs!L25 -> 2.1253263 | N142: =N141*Inputs!M25 -> 2.129577 | ... AD142: =AD141*Inputs!AC25 -> 3.3345211
B143: Ending | G143: =SUM(G141:G142) -> 1052.1 | H143: =SUM(H141:H142) -> 1054.2042 | I143: =SUM(I141:I142) -> 1056.3126 | J143: =SUM(J141:J142) -> 1058.4252 | K143: =SUM(K141:K142) -> 1060.5421 | L143: =SUM(L141:L142) -> 1062.6632 | M143: =SUM(M141:M142) -> 1064.7885 | N143: =SUM(N141:N142) -> 1066.9181 | ... AD143: =SUM(AD141:AD142) -> 1114.8416
B145: Revenue metrics
B146: Net Customer Adds | G146: =G136+G137 -> 18 | H146: =H136+H137 -> 17.6408 | I146: =I136+I137 -> 17.330776 | J146: =J136+J137 -> 17.068526 | K146: =K136+K137 -> 16.852729 | L146: =L136+L137 -> 16.682146 | M146: =M136+M137 -> 16.555614 | N146: =N136+N137 -> 16.472045 | ... AD146: =AD136+AD137 -> 22.959946
B147: Ending Customers | G147: =G138 -> 868 | H147: =H138 -> 885.6408 | I147: =I138 -> 902.97158 | J147: =J138 -> 920.0401 | K147: =K138 -> 936.89283 | L147: =L138 -> 953.57498 | M147: =M138 -> 970.13059 | N147: =N138 -> 986.60264 | ... AD147: =AD138 -> 1310.8072
B148: Customer Growth | G148: =G138/G135-1 -> 0.021176471 | H148: =H138/H135-1 -> 0.020323502 | I148: =I138/I135-1 -> 0.019568629 | J148: =J138/J135-1 -> 0.018902617 | K148: =K138/K135-1 -> 0.018317385 | L148: =L138/L135-1 -> 0.017805821 | M148: =M138/M135-1 -> 0.017361628 | N148: =N138/N135-1 -> 0.016979204 | ... AD148: =AD138/AD135-1 -> 0.01782816
B150: Beginning MRR | G150: =IF(Inputs!E181>0,Inputs!E181,'Operational Model'!F155) -> 892.5 | H150: =IF(Inputs!F181>0,Inputs!F181,'Operational Model'!G155) -> 913.2228 | I150: =IF(Inputs!G181>0,Inputs!G181,'Operational Model'!H155) -> 933.64625 | J150: =IF(Inputs!H181>0,Inputs!H181,'Operational Model'!I155) -> 953.82026 | K150: =IF(Inputs!I181>0,Inputs!I181,'Operational Model'!J155) -> 973.79366 | L150: =IF(Inputs!J181>0,Inputs!J181,'Operational Model'!K155) -> 993.61427 | M150: =IF(Inputs!K181>0,Inputs!K181,'Operational Model'!L155) -> 1013.329 | N150: =IF(Inputs!L181>0,Inputs!L181,'Operational Model'!M155) -> 1032.9839 | ... AD150: =IF(Inputs!AB181>0,Inputs!AB181,'Operational Model'!AC155) -> 1431.4513
B151: New MRR | G151: =G136*G141/1000 -> 36.75 | H151: =H136*H141/1000 -> 36.824342 | I151: =I136*I141/1000 -> 36.943102 | J151: =J136*J141/1000 -> 37.106104 | K151: =K136*K141/1000 -> 37.313227 | L151: =L136*L141/1000 -> 37.564403 | M151: =M136*M141/1000 -> 37.859621 | N151: =N136*N141/1000 -> 38.198922 | ... AD151: =AD136*AD141/1000 -> 51.286265
B152: Lost MRR | G152: =G137*G141/1000 -> -17.85 | H152: =H137*H141/1000 -> -18.264456 | I152: =I137*I141/1000 -> -18.672925 | J152: =J137*J141/1000 -> -19.076405 | K152: =K137*K141/1000 -> -19.475873 | L152: =L137*L141/1000 -> -19.872285 | M152: =M137*M141/1000 -> -20.26658 | N152: =N137*N141/1000 -> -20.659678 | ... AD152: =AD137*AD141/1000 -> -25.766123
B153: Net New MRR | G153: =G151+G152 -> 18.9 | H153: =H151+H152 -> 18.559886 | I153: =I151+I152 -> 18.270177 | J153: =J151+J152 -> 18.029699 | K153: =K151+K152 -> 17.837353 | L153: =L151+L152 -> 17.692118 | M153: =M151+M152 -> 17.593041 | N153: =N151+N152 -> 17.539244 | ... AD153: =AD151+AD152 -> 25.520142
B154: ARPU Growth MRR | G154: =G138*G142/1000 -> 1.8228 | H154: =H138*H142/1000 -> 1.8635654 | I154: =I138*I142/1000 -> 1.9038329 | J154: =J138*J142/1000 -> 1.9436999 | K154: =K138*K142/1000 -> 1.983262 | L154: =L138*L142/1000 -> 2.0226128 | M154: =M138*M142/1000 -> 2.0618441 | N154: =N138*N142/1000 -> 2.1010463 | ... AD154: =AD138*AD142/1000 -> 4.3709142
B155: Ending MRR | G155: =G150+G153+G154 -> 913.2228 | H155: =H150+H153+H154 -> 933.64625 | I155: =I150+I153+I154 -> 953.82026 | J155: =J150+J153+J154 -> 973.79366 | K155: =K150+K153+K154 -> 993.61427 | L155: =L150+L153+L154 -> 1013.329 | M155: =M150+M153+M154 -> 1032.9839 | N155: =N150+N153+N154 -> 1052.6242 | ... AD155: =AD150+AD153+AD154 -> 1461.3423
B156: MRR Growth | G156: =G155/G150-1 -> 0.023218824 | H156: =H155/H150-1 -> 0.022364149 | I156: =I155/I150-1 -> 0.021607766 | J156: =J155/J150-1 -> 0.020940422 | K156: =K155/K150-1 -> 0.02035402 | L156: =L155/L150-1 -> 0.019841432 | M156: =M155/M150-1 -> 0.019396351 | N156: =N155/N150-1 -> 0.019013163 | ... AD156: =AD155/AD150-1 -> 0.020881645
...

Sheet Valuation
B1: Gale Suer - Financial Analyst
B3: Long Term Financial Forecast
B5: All figures in EUR thousands unless stated
B6: {=CONCATENATE("Model Running: ",INDEX(Inputs!$B$15:$B$17,Inputs!$D$8)," Drivers")} -> Model Running: Base Case Drivers
I7: 2026 | J7: =I7+1 -> 2027 | K7: =J7+1 -> 2028 | L7: =K7+1 -> 2029 | M7: =L7+1 -> 2030 | N7: =M7+1 -> 2031 | O7: =N7+1 -> 2032 | P7: =O7+1 -> 2033 | Q7: =P7+1 -> 2034 | R7: =Q7+1 -> 2035 | S7: Term.
B10: Revenue | I10: =IF(I55<>0,I55,H10*(1+Inputs!D133)) -> 12275.187 | J10: =IF(J55<>0,J55,I10*(1+Inputs!E133)) -> 15669.477 | K10: =IF(K55<>0,K55,J10*(1+Inputs!F133)) -> 19273.456 | L10: =IF(L55<>0,L55,K10*(1+Inputs!G133)) -> 22935.413 | M10: =IF(M55<>0,M55,L10*(1+Inputs!H133)) -> 26605.079 | N10: =IF(N55<>0,N55,M10*(1+Inputs!I133)) -> 30063.739 | O10: =IF(O55<>0,O55,N10*(1+Inputs!J133)) -> 33070.113 | P10: =IF(P55<>0,P55,O10*(1+Inputs!K133)) -> 35715.722 | ... S10: =IF(S55<>0,S55,R10*(1+Inputs!N133)) -> 40357.337
B11: Cost of Revenue | I11: =I12-I10 -> -1887.4394 | J11: =J12-J10 -> -2393.4112 | K11: =K12-K10 -> -2794.6511 | L11: =L12-L10 -> -3210.9578 | M11: =M12-M10 -> -3591.6857 | N11: =N12-N10 -> -3908.2861 | O11: =O12-O10 -> -4299.1147 | P11: =P12-P10 -> -4643.0439 | ... S11: =S12-S10 -> -5246.4539
B12: Gross Profit | I12: =IF(I57<>0,I57,I10*Inputs!D139) -> 10387.748 | J12: =IF(J57<>0,J57,J10*Inputs!E139) -> 13276.065 | K12: =IF(K57<>0,K57,K10*Inputs!F139) -> 16478.805 | L12: =IF(L57<>0,L57,L10*Inputs!G139) -> 19724.455 | M12: =IF(M57<>0,M57,M10*Inputs!H139) -> 23013.393 | N12: =IF(N57<>0,N57,N10*Inputs!I139) -> 26155.453 | O12: =IF(O57<>0,O57,O10*Inputs!J139) -> 28770.998 | P12: =IF(P57<>0,P57,P10*Inputs!K139) -> 31072.678 | ... S12: =IF(S57<>0,S57,S10*Inputs!N139) -> 35110.884
B14: Gross Margin | I14: =I12/I10 -> 0.84623947 | J14: =J12/J10 -> 0.84725646 | K14: =K12/K10 -> 0.855 | L14: =L12/L10 -> 0.86 | M14: =M12/M10 -> 0.865 | N14: =N12/N10 -> 0.87 | O14: =O12/O10 -> 0.87 | P14: =P12/P10 -> 0.87 | ... S14: =S12/S10 -> 0.87
B16: OpEx (Sales & Marketing + R&D/Product + G&A) | I16: =I17-I12 -> -11293.285 | J16: =J17-J12 -> -13724.058 | K16: =K17-K12 -> -15515.132 | L16: =L17-L12 -> -17889.622 | M16: =M17-M12 -> -20086.835 | N16: =N17-N12 -> -21946.53 | O16: =O17-O12 -> -23314.43 | P16: =P17-P12 -> -24465.27 | ... S16: =S17-S12 -> -26232.269
B17: EBITDA | I17: =IF(I62<>0,I62,I10*Inputs!D145) -> -905.53701 | J17: =IF(J62<>0,J62,J10*Inputs!E145) -> -447.99229 | K17: =IF(K62<>0,K62,K10*Inputs!F145) -> 963.67281 | L17: =IF(L62<>0,L62,L10*Inputs!G145) -> 1834.833 | M17: =IF(M62<>0,M62,M10*Inputs!H145) -> 2926.5587 | N17: =IF(N62<>0,N62,N10*Inputs!I145) -> 4208.9235 | O17: =IF(O62<>0,O62,O10*Inputs!J145) -> 5456.5687 | P17: =IF(P62<>0,P62,P10*Inputs!K145) -> 6607.4086 | ... S17: =IF(S62<>0,S62,S10*Inputs!N145) -> 8878.6142
B19: EBITDA Margin | I19: =I17/I10 -> -0.07376971 | J19: =J17/J10 -> -0.028590125 | K19: =K17/K10 -> 0.05 | L19: =L17/L10 -> 0.08 | M19: =M17/M10 -> 0.11 | N19: =N17/N10 -> 0.14 | O19: =O17/O10 -> 0.165 | P19: =P17/P10 -> 0.185 | ... S19: =S17/S10 -> 0.22
B21: Depreciation | I21: =IF(I66<>0,I66,-I10*Inputs!D151) -> -226.08632 | J21: =IF(J66<>0,J66,-J10*Inputs!E151) -> -314.12326 | K21: =IF(K66<>0,K66,-K10*Inputs!F151) -> -385.46912 | L21: =IF(L66<>0,L66,-L10*Inputs!G151) -> -435.77284 | M21: =IF(M66<>0,M66,-M10*Inputs!H151) -> -505.4965 | N21: =IF(N66<>0,N66,-N10*Inputs!I151) -> -541.14731 | O21: =IF(O66<>0,O66,-O10*Inputs!J151) -> -595.26204 | P21: =IF(P66<>0,P66,-P10*Inputs!K151) -> -642.883 | ... S21: =IF(S66<>0,S66,-S10*Inputs!N151) -> -726.43207
B22: EBIT | I22: =I17+I21 -> -1131.6233 | J22: =J17+J21 -> -762.11555 | K22: =K17+K21 -> 578.20369 | L22: =L17+L21 -> 1399.0602 | M22: =M17+M21 -> 2421.0622 | N22: =N17+N21 -> 3667.7762 | O22: =O17+O21 -> 4861.3066 | P22: =P17+P21 -> 5964.5256 | ... S22: =S17+S21 -> 8152.1822
B24: EBIT Margin | I24: =I22/I10 -> -0.092187867 | J24: =J22/J10 -> -0.04863695 | K24: =K22/K10 -> 0.03 | L24: =L22/L10 -> 0.061 | M24: =M22/M10 -> 0.091 | N24: =N22/N10 -> 0.122 | O24: =O22/O10 -> 0.147 | P24: =P22/P10 -> 0.167 | ... S24: =S22/S10 -> 0.202
B28: Unlevered Free Cash Flow Schedule
B30: All figures in EUR thousands unless stated
B31: {=CONCATENATE("Model Running: ",INDEX(Inputs!$B$15:$B$17,Inputs!$D$8)," Drivers")} -> Model Running: Base Case Drivers
I32: 2026 | J32: =I32+1 -> 2027 | K32: =J32+1 -> 2028 | L32: =K32+1 -> 2029 | M32: =L32+1 -> 2030 | N32: =M32+1 -> 2031 | O32: =N32+1 -> 2032 | P32: =O32+1 -> 2033 | Q32: =P32+1 -> 2034 | R32: =Q32+1 -> 2035 | S32: Term.
B34: Net Working Capital
B35: Ending Net Working Capital | I35: =IF(I77<>0,I77,I10*Inputs!D163) -> -3097.9795 | J35: =IF(J77<>0,J77,J10*Inputs!E163) -> -3949.4755 | K35: =IF(K77<>0,K77,K10*Inputs!F163) -> -4818.364 | L35: =IF(L77<>0,L77,L10*Inputs!G163) -> -5733.8532 | M35: =IF(M77<>0,M77,M10*Inputs!H163) -> -6651.2697 | N35: =IF(N77<>0,N77,N10*Inputs!I163) -> -7515.9348 | O35: =IF(O77<>0,O77,O10*Inputs!J163) -> -8267.5283 | P35: =IF(P77<>0,P77,P10*Inputs!K163) -> -8928.9305 | ... S35: =IF(S77<>0,S77,S10*Inputs!N163) -> -10089.334
B36: Change in Net Working Capital | I36: =IF(I80<>0,I80,I35-H35) -> -658.97945 | J36: =IF(J80<>0,J80,J35-I35) -> -851.496 | K36: =IF(K80<>0,K80,K35-J35) -> -868.88859 | L36: =IF(L80<>0,L80,L35-K35) -> -915.48917 | M36: =IF(M80<>0,M80,M35-L35) -> -917.41651 | N36: =IF(N80<>0,N80,N35-M35) -> -864.66506 | O36: =IF(O80<>0,O80,O35-N35) -> -751.59348 | P36: =IF(P80<>0,P80,P35-O35) -> -661.40226 | ... S36: =IF(S80<>0,S80,S35-R35) -> -246.08133
B38: EBITDA Method
B39: EBITDA | I39: =I17 -> -905.53701 | J39: =J17 -> -447.99229 | K39: =K17 -> 963.67281 | L39: =L17 -> 1834.833 | M39: =M17 -> 2926.5587 | N39: =N17 -> 4208.9235 | O39: =O17 -> 5456.5687 | P39: =P17 -> 6607.4086 | ... S39: =S17 -> 8878.6142
B40: Current Tax | I40: =-MAX(I22*Inputs!$E$209,0) -> 0 | J40: =-MAX(J22*Inputs!$E$209,0) -> 0 | K40: =-MAX(K22*Inputs!$E$209,0) -> -149.17655 | L40: =-MAX(L22*Inputs!$E$209,0) -> -360.95753 | M40: =-MAX(M22*Inputs!$E$209,0) -> -624.63404 | N40: =-MAX(N22*Inputs!$E$209,0) -> -946.28625 | O40: =-MAX(O22*Inputs!$E$209,0) -> -1254.2171 | P40: =-MAX(P22*Inputs!$E$209,0) -> -1538.8476 | ... S40: =-MAX(S22*Inputs!$E$209,0) -> -2103.263
B41: Capital Expenditure | I41: =IF(I73<>0,I73,-I10*Inputs!D157) -> -245.50375 | J41: =IF(J73<>0,J73,-J10*Inputs!E157) -> -282.05058 | K41: =IF(K73<>0,K73,-K10*Inputs!F157) -> -346.92221 | L41: =IF(L73<>0,L73,-L10*Inputs!G157) -> -412.83743 | M41: =IF(M73<>0,M73,-M10*Inputs!H157) -> -478.89142 | N41: =IF(N73<>0,N73,-N10*Inputs!I157) -> -541.14731 | O41: =IF(O73<>0,O73,-O10*Inputs!J157) -> -595.26204 | P41: =IF(P73<>0,P73,-P10*Inputs!K157) -> -642.883 | ... S41: =IF(S73<>0,S73,-S10*Inputs!N157) -> -726.43207
B42: (-) Change in NWC | I42: =-I36 -> 658.97945 | J42: =-J36 -> 851.496 | K42: =-K36 -> 868.88859 | L42: =-L36 -> 915.48917 | M42: =-M36 -> 917.41651 | N42: =-N36 -> 864.66506 | O42: =-O36 -> 751.59348 | P42: =-P36 -> 661.40226 | ... S42: =-S36 -> 246.08133
B43: Unlevered Free Cash Flow | I43: =SUM(I39:I42) -> -492.0613 | J43: =SUM(J39:J42) -> 121.45313 | K43: =SUM(K39:K42) -> 1336.4626 | L43: =SUM(L39:L42) -> 1976.5272 | M43: =SUM(M39:M42) -> 2740.4497 | N43: =SUM(N39:N42) -> 3586.155 | O43: =SUM(O39:O42) -> 4358.683 | P43: =SUM(P39:P42) -> 5087.0803 | ... S43: =SUM(S39:S42) -> 6295.0005
B47: Operational Data Schedule
B49: All figures in EUR thousands unless stated
B50: {=CONCATENATE("Model Running: ",INDEX(Inputs!$B$15:$B$17,Inputs!$D$8)," Drivers")} -> Model Running: Base Case Drivers
I51: =I7 -> 2026 | J51: =J7 -> 2027
B53: Financial Forecast
B55: Revenue | I55: =SUM('Operational Model'!G10:R10) -> 12275.187 | J55: =SUM('Operational Model'!S10:AD10) -> 15669.477
B56: Cost of Revenue | I56: =SUM('Operational Model'!G12:R13) -> -1887.4394 | J56: =SUM('Operational Model'!S12:AD13) -> -2393.4112
B57: Gross Profit | I57: =SUM('Operational Model'!G14:R14) -> 10387.748 | J57: =SUM('Operational Model'!S14:AD14) -> 13276.065
B59: Gross Margin | I59: =I57/I55 -> 0.84623947 | J59: =J57/J55 -> 0.84725646
B61: OpEx (Sales & Marketing + R&D/Product + G&A) | I61: =SUM('Operational Model'!G19:R21) -> -11293.285 | J61: =SUM('Operational Model'!S19:AD21) -> -13724.058
B62: EBITDA | I62: =SUM('Operational Model'!G22:R22) -> -905.53701 | J62: =SUM('Operational Model'!S22:AD22) -> -447.99229
B64: EBITDA Margin | I64: =I62/I55 -> -0.07376971 | J64: =J62/J55 -> -0.028590125
B66: Depreciation | I66: =SUM('Operational Model'!G27:R27) -> -226.08632 | J66: =SUM('Operational Model'!S27:AD27) -> -314.12326
B67: EBIT | I67: =SUM('Operational Model'!G28:R28) -> -1131.6233 | J67: =SUM('Operational Model'!S28:AD28) -> -762.11555
B69: EBIT Margin | I69: =I67/I55 -> -0.092187867 | J69: =J67/J55 -> -0.04863695
B72: CapEx
B73: Capital Expenditures | I73: =SUM('Operational Model'!G62:R62) -> -245.50375 | J73: =SUM('Operational Model'!S62:AD62) -> -282.05058
B76: Net Working Capital
B77: Ending NWC | I77: ='Operational Model'!R381-'Operational Model'!R382-'Operational Model'!R383+'Operational Model'!R384-'Operational Model'!R412 -> -3097.9795 | J77: ='Operational Model'!AD381-'Operational Model'!AD382-'Operational Model'!AD383+'Operational Model'!AD384-'Operational Model'!AD412 -> -3949.4755
B78: Change in Net Working Capital (ex. Deferred Revenue) | I78: =-SUM('Operational Model'!G392:R392) -> 129.35841 | J78: =-SUM('Operational Model'!S392:AD392) -> 235.59577
B79: Change in Deferred Revenue | I79: =-SUM('Operational Model'!G414:R414) -> -788.33786 | J79: =-SUM('Operational Model'!S414:AD414) -> -1087.0918
B80: Change in Net Working Capital | I80: =I78+I79 -> -658.97945 | J80: =J78+J79 -> -851.496
B84: Discounted Cash Flow Schedule: Perpetuity Method
B86: All figures in EUR thousands unless stated
B87: {=CONCATENATE("Model Running: ",INDEX(Inputs!$B$15:$B$17,Inputs!$D$8)," Drivers")} -> Model Running: Base Case Drivers
F89: (DD-MM-YY) | H89: Valuation | I89: Forecast | S89: Term.
B90: Terminal Growth Rate | D90: =G272 -> 0.025 | F90: Fiscal Year End | H90: =Inputs!$E$206 -> 46112 | I90: =Inputs!$E$204 -> 46387 | J90: =EDATE(I90,12) -> 46752 | K90: =EDATE(J90,12) -> 47118 | L90: =EDATE(K90,12) -> 47483 | M90: =EDATE(L90,12) -> 47848 | N90: =EDATE(M90,12) -> 48213 | O90: =EDATE(N90,12) -> 48579 | P90: =EDATE(O90,12) -> 48944 | Q90: =EDATE(P90,12) -> 49309 | ... S90: =EDATE(R90,12) -> 50040
B91: WACC | D91: =G273 -> 0.10787893 | F91: Cash Flow Timing | H91: =$H$90 -> 46112 | I91: =Inputs!$E$205 -> 46203 | J91: =EDATE(I91,12) -> 46568 | K91: =EDATE(J91,12) -> 46934 | L91: =EDATE(K91,12) -> 47299 | M91: =EDATE(L91,12) -> 47664 | N91: =EDATE(M91,12) -> 48029 | O91: =EDATE(N91,12) -> 48395 | P91: =EDATE(O91,12) -> 48760 | Q91: =EDATE(P91,12) -> 49125 | ... S91: =EDATE(R91,12) -> 49856
B94: Unlevered Free Cash Flow | H94: 0 | I94: =I43 -> -492.0613 | J94: =J43 -> 121.45313 | K94: =K43 -> 1336.4626 | L94: =L43 -> 1976.5272 | M94: =M43 -> 2740.4497 | N94: =N43 -> 3586.155 | O94: =O43 -> 4358.683 | P94: =P43 -> 5087.0803 | ... S94: =S43 -> 6295.0005
B96: Unadjusted Cash Flow
B97: Discrete Forecast | H97: 0 | I97: =I94 -> -492.0613 | J97: =J94 -> 121.45313 | K97: =K94 -> 1336.4626 | L97: =L94 -> 1976.5272 | M97: =M94 -> 2740.4497 | N97: =N94 -> 3586.155 | O97: =O94 -> 4358.683 | P97: =P94 -> 5087.0803 | ... R97: =R94 -> 5987.8235
B98: Terminal Value | H98: 0 | I98: 0 | J98: 0 | K98: 0 | L98: 0 | M98: 0 | N98: 0 | O98: 0 | P98: 0 | Q98: 0 | R98: =S94/(D91-D90) -> 75954.175
B99: Total Cash Flow | H99: =SUM(H97:H98) -> 0 | I99: =SUM(I97:I98) -> -492.0613 | J99: =SUM(J97:J98) -> 121.45313 | K99: =SUM(K97:K98) -> 1336.4626 | L99: =SUM(L97:L98) -> 1976.5272 | M99: =SUM(M97:M98) -> 2740.4497 | N99: =SUM(N97:N98) -> 3586.155 | O99: =SUM(O97:O98) -> 4358.683 | ... R99: =SUM(R97:R98) -> 81941.999
B101: Adjusted Cash Flow
B102: Partial Period Adjustment | H102: 0 | I102: =YEARFRAC(H90,I90) -> 0.75 | J102: =YEARFRAC(I90,J90) -> 1 | K102: =YEARFRAC(J90,K90) -> 1 | L102: =YEARFRAC(K90,L90) -> 1 | M102: =YEARFRAC(L90,M90) -> 1 | N102: =YEARFRAC(M90,N90) -> 1 | O102: =YEARFRAC(N90,O90) -> 1 | P102: =YEARFRAC(O90,P90) -> 1 | ... R102: =YEARFRAC(Q90,R90) -> 1
B103: Discrete Forecast | H103: 0 | I103: =I97*I102 -> -369.04598 | J103: =J97*J102 -> 121.45313 | K103: =K97*K102 -> 1336.4626 | L103: =L97*L102 -> 1976.5272 | M103: =M97*M102 -> 2740.4497 | N103: =N97*N102 -> 3586.155 | O103: =O97*O102 -> 4358.683 | P103: =P97*P102 -> 5087.0803 | ... R103: =R97*R102 -> 5987.8235
B104: Terminal Value | H104: 0 | I104: =I98*I102 -> 0 | J104: =J98*J102 -> 0 | K104: =K98*K102 -> 0 | L104: =L98*L102 -> 0 | M104: =M98*M102 -> 0 | N104: =N98*N102 -> 0 | O104: =O98*O102 -> 0 | P104: =P98*P102 -> 0 | ... R104: =R98*R102 -> 75954.175
B105: Total Cash Flow | H105: 0 | I105: =SUM(I103:I104) -> -369.04598 | J105: =SUM(J103:J104) -> 121.45313 | K105: =SUM(K103:K104) -> 1336.4626 | L105: =SUM(L103:L104) -> 1976.5272 | M105: =SUM(M103:M104) -> 2740.4497 | N105: =SUM(N103:N104) -> 3586.155 | O105: =SUM(O103:O104) -> 4358.683 | P105: =SUM(P103:P104) -> 5087.0803 | ... R105: =SUM(R103:R104) -> 81941.999
B107: Discounted Cash Flow
B108: Years for Discounting | H108: 0 | I108: =H108+YEARFRAC(H91,I91) -> 0.25 | J108: =I108+YEARFRAC(I91,J91) -> 1.25 | K108: =J108+YEARFRAC(J91,K91) -> 2.25 | L108: =K108+YEARFRAC(K91,L91) -> 3.25 | M108: =L108+YEARFRAC(L91,M91) -> 4.25 | N108: =M108+YEARFRAC(M91,N91) -> 5.25 | O108: =N108+YEARFRAC(N91,O91) -> 6.25 | P108: =O108+YEARFRAC(O91,P91) -> 7.25 | ... R108: =Q108+YEARFRAC(Q91,R91) -> 9.25
B109: Forecast | H109: 0 | I109: =I103/(1+$D$91)^I108 -> -359.71405 | J109: =J103/(1+$D$91)^J108 -> 106.85463 | K109: =K103/(1+$D$91)^K108 -> 1061.3268 | L109: =L103/(1+$D$91)^L108 -> 1416.7813 | M109: =M103/(1+$D$91)^M108 -> 1773.085 | N109: =N103/(1+$D$91)^N108 -> 2094.3269 | O109: =O103/(1+$D$91)^O108 -> 2297.621 | P109: =P103/(1+$D$91)^P108 -> 2420.4683 | ... R109: =R103/(1+$D$91)^R108 -> 2321.2141
B110: Terminal Value | H110: 0 | I110: =I104/(1+$D$91)^I108 -> 0 | J110: =J104/(1+$D$91)^J108 -> 0 | K110: =K104/(1+$D$91)^K108 -> 0 | L110: =L104/(1+$D$91)^L108 -> 0 | M110: =M104/(1+$D$91)^M108 -> 0 | N110: =N104/(1+$D$91)^N108 -> 0 | O110: =O104/(1+$D$91)^O108 -> 0 | P110: =P104/(1+$D$91)^P108 -> 0 | ... R110: =R104/(1+$D$91)^R108 -> 29444.072
B111: Total Cash Flow | H111: =SUM(H109:H110) -> 0 | I111: =SUM(I109:I110) -> -359.71405 | J111: =SUM(J109:J110) -> 106.85463 | K111: =SUM(K109:K110) -> 1061.3268 | L111: =SUM(L109:L110) -> 1416.7813 | M111: =SUM(M109:M110) -> 1773.085 | N111: =SUM(N109:N110) -> 2094.3269 | O111: =SUM(O109:O110) -> 2297.621 | ... R111: =SUM(R109:R110) -> 31765.286
H115: Enterprise Value | M115: Equity Value
H116: PV of Discrete | J116: =K116/$K$118 -> 0.34571423 | K116: =SUM(I109:R109) -> 15557.78 | M116: Enterprise Value | P116: =K121 -> 44981.392
H117: PV of Terminal | J117: =K117/$K$118 -> 0.65428577 | K117: =SUM(I110:R110) -> 29444.072 | M117: Cash | P117: ='Operational Model'!I90 -> 3840.0634
H118: Enterprise Value | J118: =K118/$K$118 -> 1 | K118: =SUM(K116:K117) -> 45001.852 | M118: Debt | P118: =-Inputs!E200 -> 0
M119: Equity Value | P119: =SUM(P116:P118) -> 48821.455
H120: Manual Method | K120: =SUM(I111:R111) -> 45001.852
H121: XNPV Function | K121: =XNPV(D91,H105:R105,H91:R91) -> 44981.392
S124: Due to the treatment of leap years, XNPV differs slightly from the Manual Method.
B128: Discounted Cash Flow Schedule: Multiple Method
B130: All figures in EUR thousands unless stated
B131: {=CONCATENATE("Model Running: ",INDEX(Inputs!$B$15:$B$17,Inputs!$D$8)," Drivers")} -> Model Running: Base Case Drivers
B133: EV/EBITDA Multiple | D133: =G274 -> 9 | F133: (DD-MM-YY) | H133: Valuation | I133: Forecast | S133: Term.
B134: WACC | D134: =G273 -> 0.10787893 | F134: Fiscal Year End | H134: =Inputs!$E$206 -> 46112 | I134: =Inputs!$E$204 -> 46387 | J134: =EDATE(I134,12) -> 46752 | K134: =EDATE(J134,12) -> 47118 | L134: =EDATE(K134,12) -> 47483 | M134: =EDATE(L134,12) -> 47848 | N134: =EDATE(M134,12) -> 48213 | O134: =EDATE(N134,12) -> 48579 | P134: =EDATE(O134,12) -> 48944 | Q134: =EDATE(P134,12) -> 49309 | ... S134: =EDATE(R134,12) -> 50040
B135: Terminal Adjustment | D135: =YEARFRAC(S134,S135) -> 0.5 | F135: Cash Flow Timing | H135: =$H$90 -> 46112 | I135: =Inputs!$E$205 -> 46203 | J135: =EDATE(I135,12) -> 46568 | K135: =EDATE(J135,12) -> 46934 | L135: =EDATE(K135,12) -> 47299 | M135: =EDATE(L135,12) -> 47664 | N135: =EDATE(M135,12) -> 48029 | O135: =EDATE(N135,12) -> 48395 | P135: =EDATE(O135,12) -> 48760 | Q135: =EDATE(P135,12) -> 49125 | ... S135: =EDATE(R135,12) -> 49856
B138: Unlevered Free Cash Flow | I138: =I43 -> -492.0613 | J138: =J43 -> 121.45313 | K138: =K43 -> 1336.4626 | L138: =L43 -> 1976.5272 | M138: =M43 -> 2740.4497 | N138: =N43 -> 3586.155 | O138: =O43 -> 4358.683 | P138: =P43 -> 5087.0803 | ... S138: =S43 -> 6295.0005
B139: EBITDA | S139: =S17 -> 8878.6142
B141: Unadjusted Cash Flow
B142: Discrete Forecast | H142: 0 | I142: =I138 -> -492.0613 | J142: =J138 -> 121.45313 | K142: =K138 -> 1336.4626 | L142: =L138 -> 1976.5272 | M142: =M138 -> 2740.4497 | N142: =N138 -> 3586.155 | O142: =O138 -> 4358.683 | P142: =P138 -> 5087.0803 | ... S142: =S138 -> 6295.0005
B143: Terminal Value | H143: 0 | I143: 0 | J143: 0 | K143: 0 | L143: 0 | M143: 0 | N143: 0 | O143: 0 | P143: 0 | Q143: 0 | R143: 0 | S143: =S139*D133/(1+D134)^D135 -> 75917.438
B144: Total Cash Flow | H144: =SUM(H142:H143) -> 0 | I144: =SUM(I142:I143) -> -492.0613 | J144: =SUM(J142:J143) -> 121.45313 | K144: =SUM(K142:K143) -> 1336.4626 | L144: =SUM(L142:L143) -> 1976.5272 | M144: =SUM(M142:M143) -> 2740.4497 | N144: =SUM(N142:N143) -> 3586.155 | O144: =SUM(O142:O143) -> 4358.683 | ... S144: =SUM(S142:S143) -> 82212.439
B146: Adjusted Cash Flow
B147: Partial Period Adjustment | H147: 0 | I147: =YEARFRAC(H134,I134) -> 0.75 | J147: =YEARFRAC(I134,J134) -> 1 | K147: =YEARFRAC(J134,K134) -> 1 | L147: =YEARFRAC(K134,L134) -> 1 | M147: =YEARFRAC(L134,M134) -> 1 | N147: =YEARFRAC(M134,N134) -> 1 | O147: =YEARFRAC(N134,O134) -> 1 | P147: =YEARFRAC(O134,P134) -> 1 | ... S147: =YEARFRAC(R134,S134) -> 1
B148: Discrete Forecast | H148: 0 | I148: =I142*I147 -> -369.04598 | J148: =J142*J147 -> 121.45313 | K148: =K142*K147 -> 1336.4626 | L148: =L142*L147 -> 1976.5272 | M148: =M142*M147 -> 2740.4497 | N148: =N142*N147 -> 3586.155 | O148: =O142*O147 -> 4358.683 | P148: =P142*P147 -> 5087.0803 | ... S148: =S142*S147 -> 6295.0005
B149: Terminal Value | H149: 0 | I149: =I143*I147 -> 0 | J149: =J143*J147 -> 0 | K149: =K143*K147 -> 0 | L149: =L143*L147 -> 0 | M149: =M143*M147 -> 0 | N149: =N143*N147 -> 0 | O149: =O143*O147 -> 0 | P149: =P143*P147 -> 0 | ... S149: =S143*S147 -> 75917.438
B150: Total Cash Flow | H150: =SUM(H148:H149) -> 0 | I150: =SUM(I148:I149) -> -369.04598 | J150: =SUM(J148:J149) -> 121.45313 | K150: =SUM(K148:K149) -> 1336.4626 | L150: =SUM(L148:L149) -> 1976.5272 | M150: =SUM(M148:M149) -> 2740.4497 | N150: =SUM(N148:N149) -> 3586.155 | O150: =SUM(O148:O149) -> 4358.683 | ... S150: =SUM(S148:S149) -> 82212.439
B152: Discounted Cash Flow
B153: Years for Discounting | H153: 0 | I153: =H153+YEARFRAC(H135,I135) -> 0.25 | J153: =I153+YEARFRAC(I135,J135) -> 1.25 | K153: =J153+YEARFRAC(J135,K135) -> 2.25 | L153: =K153+YEARFRAC(K135,L135) -> 3.25 | M153: =L153+YEARFRAC(L135,M135) -> 4.25 | N153: =M153+YEARFRAC(M135,N135) -> 5.25 | O153: =N153+YEARFRAC(N135,O135) -> 6.25 | P153: =O153+YEARFRAC(O135,P135) -> 7.25 | ... S153: =R153+YEARFRAC(R135,S135) -> 10.25
B154: Forecast | H154: 0 | I154: =I148/(1+$D$134)^I$153 -> -359.71405 | J154: =J148/(1+$D$134)^J$153 -> 106.85463 | K154: =K148/(1+$D$134)^K$153 -> 1061.3268 | L154: =L148/(1+$D$134)^L$153 -> 1416.7813 | M154: =M148/(1+$D$134)^M$153 -> 1773.085 | N154: =N148/(1+$D$134)^N$153 -> 2094.3269 | O154: =O148/(1+$D$134)^O$153 -> 2297.621 | P154: =P148/(1+$D$134)^P$153 -> 2420.4683 | ... S154: =S148/(1+$D$134)^S$153 -> 2202.6712
B155: Terminal Value | H155: 0 | I155: =I149/(1+$D$134)^I$153 -> 0 | J155: =J149/(1+$D$134)^J$153 -> 0 | K155: =K149/(1+$D$134)^K$153 -> 0 | L155: =L149/(1+$D$134)^L$153 -> 0 | M155: =M149/(1+$D$134)^M$153 -> 0 | N155: =N149/(1+$D$134)^N$153 -> 0 | O155: =O149/(1+$D$134)^O$153 -> 0 | P155: =P149/(1+$D$134)^P$153 -> 0 | ... S155: =S149/(1+$D$134)^S$153 -> 26564.121
...
